[{"id": 1, "name": "Jacquard"}, {"id": 2, "name": "couch", "parent": 1}, {"id": 3, "name": "couch_n", "parent": 3, "size": 381}, {"id": 4, "name": "sectional", "parent": 3, "size": 13}, {"id": 5, "name": "loveseat", "parent": 3, "size": 19}, {"id": 6, "name": "table", "parent": 1}, {"id": 7, "name": "roundtable", "parent": 7, "size": 35}, {"id": 8, "name": "table_n", "parent": 7, "size": 89}, {"id": 9, "name": "coffeetable", "parent": 7, "size": 82}, {"id": 10, "name": "bartable", "parent": 7, "size": 1}, {"id": 11, "name": "diningtable", "parent": 7, "size": 91}, {"id": 12, "name": "endtable", "parent": 7, "size": 91}, {"id": 13, "name": "gametable", "parent": 7, "size": 25}, {"id": 14, "name": "accenttable", "parent": 7, "size": 67}, {"id": 15, "name": "outdoortable", "parent": 7, "size": 8}, {"id": 16, "name": "desk", "parent": 7, "size": 191}, {"id": 17, "name": "chestofdrawers", "parent": 7, "size": 144}, {"id": 18, "name": "tv", "parent": 1}, {"id": 19, "name": "tv_n", "parent": 19, "size": 205}, {"id": 20, "name": "others", "parent": 1}, {"id": 21, "name": "stevedore", "parent": 21, "size": 2}, {"id": 22, "name": "brain", "parent": 21, "size": 4}, {"id": 23, "name": "stapler", "parent": 21, "size": 38}, {"id": 24, "name": "wash", "parent": 21, "size": 2}, {"id": 25, "name": "holder", "parent": 21, "size": 44}, {"id": 26, "name": "others_n", "parent": 21, "size": 836}, {"id": 27, "name": "cabana", "parent": 21, "size": 4}, {"id": 28, "name": "partition", "parent": 21, "size": 8}, {"id": 29, "name": "rack", "parent": 21, "size": 36}, {"id": 30, "name": "decker", "parent": 21, "size": 1}, {"id": 31, "name": "jar", "parent": 21, "size": 9}, {"id": 32, "name": "knocker", "parent": 21, "size": 1}, {"id": 33, "name": "doorknob", "parent": 21, "size": 2}, {"id": 34, "name": "loudspeaker", "parent": 21, "size": 1}, {"id": 35, "name": "towelring", "parent": 21, "size": 6}, {"id": 36, "name": "apple", "parent": 21, "size": 5}, {"id": 37, "name": "consoletable", "parent": 21, "size": 6}, {"id": 38, "name": "barbecue", "parent": 21, "size": 2}, {"id": 39, "name": "bucket", "parent": 21, "size": 18}, {"id": 40, "name": "bracket", "parent": 21, "size": 5}, {"id": 41, "name": "door", "parent": 21, "size": 2}, {"id": 42, "name": "wagon", "parent": 21, "size": 2}, {"id": 43, "name": "detergent", "parent": 21, "size": 7}, {"id": 44, "name": "key", "parent": 21, "size": 11}, {"id": 45, "name": "gazebo", "parent": 21, "size": 2}, {"id": 46, "name": "box", "parent": 21, "size": 31}, {"id": 47, "name": "ant", "parent": 21, "size": 4}, {"id": 48, "name": "scissors", "parent": 21, "size": 6}, {"id": 49, "name": "product", "parent": 21, "size": 2}, {"id": 50, "name": "desk", "parent": 21, "size": 191}, {"id": 51, "name": "basket", "parent": 21, "size": 23}, {"id": 52, "name": "lightbulb", "parent": 21, "size": 10}, {"id": 53, "name": "player", "parent": 21, "size": 8}, {"id": 54, "name": "balcony", "parent": 21, "size": 2}, {"id": 55, "name": "pin", "parent": 21, "size": 2}, {"id": 56, "name": "hookah", "parent": 21, "size": 2}, {"id": 57, "name": "ipod", "parent": 21, "size": 50}, {"id": 58, "name": "watchtower", "parent": 21, "size": 1}, {"id": 59, "name": "ship", "parent": 21, "size": 19}, {"id": 60, "name": "softdrink", "parent": 21, "size": 2}, {"id": 61, "name": "toasteroven", "parent": 21, "size": 2}, {"id": 62, "name": "diskdrive", "parent": 21, "size": 4}, {"id": 63, "name": "flashlight", "parent": 21, "size": 16}, {"id": 64, "name": "point", "parent": 21, "size": 1}, {"id": 65, "name": "malechild", "parent": 21, "size": 1}, {"id": 66, "name": "ladle", "parent": 21, "size": 2}, {"id": 67, "name": "humanbody", "parent": 21, "size": 1}, {"id": 68, "name": "arcademachine", "parent": 21, "size": 27}, {"id": 69, "name": "split", "parent": 21, "size": 1}, {"id": 70, "name": "smokestack", "parent": 21, "size": 3}, {"id": 71, "name": "shower", "parent": 21, "size": 7}, {"id": 72, "name": "lock", "parent": 21, "size": 11}, {"id": 73, "name": "air", "parent": 21, "size": 3}, {"id": 74, "name": "planter", "parent": 21, "size": 17}, {"id": 75, "name": "airconditioner", "parent": 21, "size": 10}, {"id": 76, "name": "cuttingboard", "parent": 21, "size": 2}, {"id": 77, "name": "cocacola", "parent": 21, "size": 1}, {"id": 78, "name": "station", "parent": 21, "size": 2}, {"id": 79, "name": "toilet", "parent": 21, "size": 52}, {"id": 80, "name": "massif", "parent": 21, "size": 1}, {"id": 81, "name": "sock", "parent": 21, "size": 1}, {"id": 82, "name": "machine", "parent": 21, "size": 19}, {"id": 83, "name": "kangaroo", "parent": 21, "size": 1}, {"id": 84, "name": "quiver", "parent": 21, "size": 2}, {"id": 85, "name": "bowl", "parent": 21, "size": 35}, {"id": 86, "name": "ruler", "parent": 21, "size": 10}, {"id": 87, "name": "dish", "parent": 21, "size": 5}, {"id": 88, "name": "beanbag", "parent": 21, "size": 9}, {"id": 89, "name": "chessboard", "parent": 21, "size": 33}, {"id": 90, "name": "motorcycle", "parent": 21, "size": 10}, {"id": 91, "name": "wine", "parent": 21, "size": 1}, {"id": 92, "name": "pencil", "parent": 21, "size": 86}, {"id": 93, "name": "projector", "parent": 21, "size": 15}, {"id": 94, "name": "scott", "parent": 21, "size": 1}, {"id": 95, "name": "californium", "parent": 21, "size": 1}, {"id": 96, "name": "memory", "parent": 21, "size": 2}, {"id": 97, "name": "wheel", "parent": 21, "size": 6}, {"id": 98, "name": "bale", "parent": 21, "size": 1}, {"id": 99, "name": "planet", "parent": 21, "size": 17}, {"id": 100, "name": "militarypost", "parent": 21, "size": 6}, {"id": 101, "name": "centrifuge", "parent": 21, "size": 1}, {"id": 102, "name": "rabbithutch", "parent": 21, "size": 2}, {"id": 103, "name": "labbench", "parent": 21, "size": 1}, {"id": 104, "name": "crisscross", "parent": 21, "size": 2}, {"id": 105, "name": "shelf", "parent": 21, "size": 25}, {"id": 106, "name": "compass", "parent": 21, "size": 6}, {"id": 107, "name": "knob", "parent": 21, "size": 1}, {"id": 108, "name": "vase", "parent": 21, "size": 168}, {"id": 109, "name": "telescopewithtripod", "parent": 21, "size": 4}, {"id": 110, "name": "radiator", "parent": 21, "size": 8}, {"id": 111, "name": "rock", "parent": 21, "size": 10}, {"id": 112, "name": "flask", "parent": 21, "size": 12}, {"id": 113, "name": "automaton", "parent": 21, "size": 8}, {"id": 114, "name": "grenade", "parent": 21, "size": 3}, {"id": 115, "name": "firealarm", "parent": 21, "size": 2}, {"id": 116, "name": "soldier", "parent": 21, "size": 1}, {"id": 117, "name": "rod", "parent": 21, "size": 1}, {"id": 118, "name": "catapult", "parent": 21, "size": 2}, {"id": 119, "name": "case", "parent": 21, "size": 4}, {"id": 120, "name": "dryer", "parent": 21, "size": 7}, {"id": 121, "name": "folder", "parent": 21, "size": 2}, {"id": 122, "name": "crib", "parent": 21, "size": 8}, {"id": 123, "name": "flag", "parent": 21, "size": 3}, {"id": 124, "name": "amplifier", "parent": 21, "size": 1}, {"id": 125, "name": "briefcase", "parent": 21, "size": 2}, {"id": 126, "name": "pencilsharpener", "parent": 21, "size": 13}, {"id": 127, "name": "mutant", "parent": 21, "size": 1}, {"id": 128, "name": "mouse", "parent": 21, "size": 5}, {"id": 129, "name": "dart", "parent": 21, "size": 5}, {"id": 130, "name": "ball", "parent": 21, "size": 24}, {"id": 131, "name": "toothbrush", "parent": 21, "size": 5}, {"id": 132, "name": "dressingtable", "parent": 21, "size": 2}, {"id": 133, "name": "gloveleather", "parent": 21, "size": 1}, {"id": 134, "name": "drumset", "parent": 21, "size": 11}, {"id": 135, "name": "anvil", "parent": 21, "size": 7}, {"id": 136, "name": "pendulum", "parent": 21, "size": 2}, {"id": 137, "name": "warthog", "parent": 21, "size": 1}, {"id": 138, "name": "table", "parent": 21, "size": 89}, {"id": 139, "name": "cell", "parent": 21, "size": 2}, {"id": 140, "name": "penny", "parent": 21, "size": 1}, {"id": 141, "name": "bar", "parent": 21, "size": 7}, {"id": 142, "name": "bandsaw", "parent": 21, "size": 2}, {"id": 143, "name": "model", "parent": 21, "size": 16}, {"id": 144, "name": "ashcan", "parent": 21, "size": 5}, {"id": 145, "name": "molotovcocktail", "parent": 21, "size": 1}, {"id": 146, "name": "cougar", "parent": 21, "size": 1}, {"id": 147, "name": "server", "parent": 21, "size": 2}, {"id": 148, "name": "mezzanine", "parent": 21, "size": 1}, {"id": 149, "name": "handdryer", "parent": 21, "size": 3}, {"id": 150, "name": "controlcenter", "parent": 21, "size": 1}, {"id": 151, "name": "cross", "parent": 21, "size": 3}, {"id": 152, "name": "toaster", "parent": 21, "size": 3}, {"id": 153, "name": "magazine", "parent": 21, "size": 4}, {"id": 154, "name": "mosquito", "parent": 21, "size": 1}, {"id": 155, "name": "tableland", "parent": 21, "size": 1}, {"id": 156, "name": "king", "parent": 21, "size": 3}, {"id": 157, "name": "cup", "parent": 21, "size": 41}, {"id": 158, "name": "head", "parent": 21, "size": 13}, {"id": 159, "name": "dwelling", "parent": 21, "size": 2}, {"id": 160, "name": "destroyer", "parent": 21, "size": 2}, {"id": 161, "name": "globe", "parent": 21, "size": 18}, {"id": 162, "name": "hob", "parent": 21, "size": 1}, {"id": 163, "name": "flagpole", "parent": 21, "size": 38}, {"id": 164, "name": "cart", "parent": 21, "size": 11}, {"id": 165, "name": "dispenser", "parent": 21, "size": 5}, {"id": 166, "name": "candle", "parent": 21, "size": 54}, {"id": 167, "name": "factory", "parent": 21, "size": 1}, {"id": 168, "name": "gurney", "parent": 21, "size": 1}, {"id": 169, "name": "connection", "parent": 21, "size": 2}, {"id": 170, "name": "boot", "parent": 21, "size": 2}, {"id": 171, "name": "grillroom", "parent": 21, "size": 4}, {"id": 172, "name": "electricorgan", "parent": 21, "size": 2}, {"id": 173, "name": "vessel", "parent": 21, "size": 2}, {"id": 174, "name": "money", "parent": 21, "size": 2}, {"id": 175, "name": "pottery", "parent": 21, "size": 4}, {"id": 176, "name": "crest", "parent": 21, "size": 2}, {"id": 177, "name": "vendingmachine", "parent": 21, "size": 4}, {"id": 178, "name": "render", "parent": 21, "size": 2}, {"id": 179, "name": "musicbox", "parent": 21, "size": 1}, {"id": 180, "name": "circuitboard", "parent": 21, "size": 1}, {"id": 181, "name": "tapemeasure", "parent": 21, "size": 10}, {"id": 182, "name": "universe", "parent": 21, "size": 9}, {"id": 183, "name": "tripod", "parent": 21, "size": 4}, {"id": 184, "name": "ricecooker", "parent": 21, "size": 4}, {"id": 185, "name": "skitow", "parent": 21, "size": 3}, {"id": 186, "name": "deer", "parent": 21, "size": 1}, {"id": 187, "name": "firecracker", "parent": 21, "size": 1}, {"id": 188, "name": "microscope", "parent": 21, "size": 3}, {"id": 189, "name": "bling", "parent": 21, "size": 1}, {"id": 190, "name": "channel", "parent": 21, "size": 2}, {"id": 191, "name": "cytosine", "parent": 21, "size": 1}, {"id": 192, "name": "blender", "parent": 21, "size": 5}, {"id": 193, "name": "woman", "parent": 21, "size": 5}, {"id": 194, "name": "windowblind", "parent": 21, "size": 1}, {"id": 195, "name": "hood", "parent": 21, "size": 5}, {"id": 196, "name": "housing", "parent": 21, "size": 1}, {"id": 197, "name": "rifle", "parent": 21, "size": 4}, {"id": 198, "name": "coffeemaker", "parent": 21, "size": 10}, {"id": 199, "name": "cabinet", "parent": 21, "size": 154}, {"id": 200, "name": "framework", "parent": 21, "size": 1}, {"id": 201, "name": "ashtray", "parent": 21, "size": 3}, {"id": 202, "name": "vitamind", "parent": 21, "size": 1}, {"id": 203, "name": "teacup", "parent": 21, "size": 9}, {"id": 204, "name": "papermoney", "parent": 21, "size": 5}, {"id": 205, "name": "stand", "parent": 21, "size": 14}, {"id": 206, "name": "mixer", "parent": 21, "size": 9}, {"id": 207, "name": "beerbarrel", "parent": 21, "size": 2}, {"id": 208, "name": "gasrange", "parent": 21, "size": 2}, {"id": 209, "name": "waterfaucet", "parent": 21, "size": 2}, {"id": 210, "name": "drive", "parent": 21, "size": 4}, {"id": 211, "name": "frame", "parent": 21, "size": 3}, {"id": 212, "name": "bleachingagent", "parent": 21, "size": 1}, {"id": 213, "name": "bear", "parent": 21, "size": 17}, {"id": 214, "name": "tower", "parent": 21, "size": 9}, {"id": 215, "name": "switch", "parent": 21, "size": 7}, {"id": 216, "name": "control", "parent": 21, "size": 5}, {"id": 217, "name": "broom", "parent": 21, "size": 2}, {"id": 218, "name": "portable", "parent": 21, "size": 3}, {"id": 219, "name": "shackle", "parent": 21, "size": 6}, {"id": 220, "name": "earphone", "parent": 21, "size": 2}, {"id": 221, "name": "bottle", "parent": 21, "size": 49}, {"id": 222, "name": "turret", "parent": 21, "size": 2}, {"id": 223, "name": "gold", "parent": 21, "size": 1}, {"id": 224, "name": "peppershaker", "parent": 21, "size": 3}, {"id": 225, "name": "abacus", "parent": 21, "size": 4}, {"id": 226, "name": "headset", "parent": 21, "size": 2}, {"id": 227, "name": "beverage", "parent": 21, "size": 2}, {"id": 228, "name": "crate", "parent": 21, "size": 5}, {"id": 229, "name": "skateboard", "parent": 21, "size": 24}, {"id": 230, "name": "thumbtack", "parent": 21, "size": 12}, {"id": 231, "name": "ironing", "parent": 21, "size": 1}, {"id": 232, "name": "trailingarbutus", "parent": 21, "size": 1}, {"id": 233, "name": "stadium", "parent": 21, "size": 1}, {"id": 234, "name": "pod", "parent": 21, "size": 1}, {"id": 235, "name": "hook", "parent": 21, "size": 4}, {"id": 236, "name": "canyon", "parent": 21, "size": 2}, {"id": 237, "name": "miniskirt", "parent": 21, "size": 2}, {"id": 238, "name": "homo", "parent": 21, "size": 3}, {"id": 239, "name": "booth", "parent": 21, "size": 12}, {"id": 240, "name": "center", "parent": 21, "size": 3}, {"id": 241, "name": "hammer", "parent": 21, "size": 27}, {"id": 242, "name": "dustpan", "parent": 21, "size": 3}, {"id": 243, "name": "closedchain", "parent": 21, "size": 1}, {"id": 244, "name": "doublebed", "parent": 21, "size": 20}, {"id": 245, "name": "forklift", "parent": 21, "size": 2}, {"id": 246, "name": "perfume", "parent": 21, "size": 14}, {"id": 247, "name": "stageset", "parent": 21, "size": 4}, {"id": 248, "name": "bookcase", "parent": 21, "size": 21}, {"id": 249, "name": "tapedispenser", "parent": 21, "size": 11}, {"id": 250, "name": "urn", "parent": 21, "size": 7}, {"id": 251, "name": "sprocket", "parent": 21, "size": 1}, {"id": 252, "name": "light", "parent": 21, "size": 7}, {"id": 253, "name": "link", "parent": 21, "size": 5}, {"id": 254, "name": "surrogate", "parent": 21, "size": 1}, {"id": 255, "name": "game", "parent": 21, "size": 4}, {"id": 256, "name": "telescope", "parent": 21, "size": 11}, {"id": 257, "name": "hoop", "parent": 21, "size": 1}, {"id": 258, "name": "tree", "parent": 21, "size": 2}, {"id": 259, "name": "seashore", "parent": 21, "size": 1}, {"id": 260, "name": "cradle", "parent": 21, "size": 10}, {"id": 261, "name": "squirrel", "parent": 21, "size": 1}, {"id": 262, "name": "cone", "parent": 21, "size": 1}, {"id": 263, "name": "wood", "parent": 21, "size": 6}, {"id": 264, "name": "spraypaint", "parent": 21, "size": 1}, {"id": 265, "name": "wall", "parent": 21, "size": 2}, {"id": 266, "name": "fountain", "parent": 21, "size": 12}, {"id": 267, "name": "keg", "parent": 21, "size": 2}, {"id": 268, "name": "fireplug", "parent": 21, "size": 2}, {"id": 269, "name": "restaurant", "parent": 21, "size": 4}, {"id": 270, "name": "duplicator", "parent": 21, "size": 1}, {"id": 271, "name": "dictionary", "parent": 21, "size": 1}, {"id": 272, "name": "type", "parent": 21, "size": 3}, {"id": 273, "name": "scanner", "parent": 21, "size": 6}, {"id": 274, "name": "hutch", "parent": 21, "size": 3}, {"id": 275, "name": "dartboard", "parent": 21, "size": 7}, {"id": 276, "name": "background", "parent": 21, "size": 2}, {"id": 277, "name": "jigsaw", "parent": 21, "size": 1}, {"id": 278, "name": "mule", "parent": 21, "size": 3}, {"id": 279, "name": "rolodex", "parent": 21, "size": 1}, {"id": 280, "name": "teaurn", "parent": 21, "size": 1}, {"id": 281, "name": "trunk", "parent": 21, "size": 5}, {"id": 282, "name": "drawers", "parent": 21, "size": 2}, {"id": 283, "name": "boat", "parent": 21, "size": 5}, {"id": 284, "name": "basilisk", "parent": 21, "size": 1}, {"id": 285, "name": "seaborgium", "parent": 21, "size": 1}, {"id": 286, "name": "pad", "parent": 21, "size": 12}, {"id": 287, "name": "carrel", "parent": 21, "size": 2}, {"id": 288, "name": "golfcart", "parent": 21, "size": 1}, {"id": 289, "name": "archives", "parent": 21, "size": 1}, {"id": 290, "name": "colors", "parent": 21, "size": 2}, {"id": 291, "name": "credenza", "parent": 21, "size": 14}, {"id": 292, "name": "conveyance", "parent": 21, "size": 3}, {"id": 293, "name": "necktie", "parent": 21, "size": 2}, {"id": 294, "name": "river", "parent": 21, "size": 1}, {"id": 295, "name": "dragon", "parent": 21, "size": 4}, {"id": 296, "name": "synthesizer", "parent": 21, "size": 2}, {"id": 297, "name": "ocarina", "parent": 21, "size": 1}, {"id": 298, "name": "pylon", "parent": 21, "size": 1}, {"id": 299, "name": "helmet", "parent": 21, "size": 16}, {"id": 300, "name": "radioactivewaste", "parent": 21, "size": 1}, {"id": 301, "name": "object", "parent": 21, "size": 1}, {"id": 302, "name": "tile", "parent": 21, "size": 1}, {"id": 303, "name": "disk", "parent": 21, "size": 3}, {"id": 304, "name": "interceptor", "parent": 21, "size": 1}, {"id": 305, "name": "bill", "parent": 21, "size": 2}, {"id": 306, "name": "fryingpan", "parent": 21, "size": 1}, {"id": 307, "name": "toilettissue", "parent": 21, "size": 2}, {"id": 308, "name": "screen", "parent": 21, "size": 10}, {"id": 309, "name": "wrench", "parent": 21, "size": 6}, {"id": 310, "name": "corona", "parent": 21, "size": 1}, {"id": 311, "name": "dressing", "parent": 21, "size": 3}, {"id": 312, "name": "vela", "parent": 21, "size": 1}, {"id": 313, "name": "bookshelf", "parent": 21, "size": 3}, {"id": 314, "name": "cube", "parent": 21, "size": 8}, {"id": 315, "name": "macintosh", "parent": 21, "size": 1}, {"id": 316, "name": "upright", "parent": 21, "size": 2}, {"id": 317, "name": "art", "parent": 21, "size": 2}, {"id": 318, "name": "condor", "parent": 21, "size": 1}, {"id": 319, "name": "stepstool", "parent": 21, "size": 3}, {"id": 320, "name": "tidy", "parent": 21, "size": 1}, {"id": 321, "name": "enclosure", "parent": 21, "size": 2}, {"id": 322, "name": "dog", "parent": 21, "size": 12}, {"id": 323, "name": "radioreceiver", "parent": 21, "size": 3}, {"id": 324, "name": "razor", "parent": 21, "size": 3}, {"id": 325, "name": "overheadprojector", "parent": 21, "size": 1}, {"id": 326, "name": "tail", "parent": 21, "size": 1}, {"id": 327, "name": "service", "parent": 21, "size": 2}, {"id": 328, "name": "newspaper", "parent": 21, "size": 1}, {"id": 329, "name": "decoration", "parent": 21, "size": 3}, {"id": 330, "name": "star", "parent": 21, "size": 10}, {"id": 331, "name": "design", "parent": 21, "size": 8}, {"id": 332, "name": "dais", "parent": 21, "size": 2}, {"id": 333, "name": "bell", "parent": 21, "size": 2}, {"id": 334, "name": "barrel", "parent": 21, "size": 8}, {"id": 335, "name": "heater", "parent": 21, "size": 10}, {"id": 336, "name": "making", "parent": 21, "size": 1}, {"id": 337, "name": "plunger", "parent": 21, "size": 4}, {"id": 338, "name": "cartridge", "parent": 21, "size": 2}, {"id": 339, "name": "fighter", "parent": 21, "size": 3}, {"id": 340, "name": "whiteboard", "parent": 21, "size": 5}, {"id": 341, "name": "airdock", "parent": 21, "size": 4}, {"id": 342, "name": "cheese", "parent": 21, "size": 2}, {"id": 343, "name": "eraser", "parent": 21, "size": 14}, {"id": 344, "name": "luggagecompartment", "parent": 21, "size": 1}, {"id": 345, "name": "cashregister", "parent": 21, "size": 4}, {"id": 346, "name": "column", "parent": 21, "size": 2}, {"id": 347, "name": "drawer", "parent": 21, "size": 2}, {"id": 348, "name": "edition", "parent": 21, "size": 1}, {"id": 349, "name": "sweater", "parent": 21, "size": 2}, {"id": 350, "name": "wardrobe", "parent": 21, "size": 4}, {"id": 351, "name": "dinosaur", "parent": 21, "size": 2}, {"id": 352, "name": "hawk", "parent": 21, "size": 1}, {"id": 353, "name": "cord", "parent": 21, "size": 1}, {"id": 354, "name": "amphora", "parent": 21, "size": 1}, {"id": 355, "name": "memorial", "parent": 21, "size": 2}, {"id": 356, "name": "bite", "parent": 21, "size": 2}, {"id": 357, "name": "liquidcrystaldisplay", "parent": 21, "size": 3}, {"id": 358, "name": "bench", "parent": 21, "size": 91}, {"id": 359, "name": "camera", "parent": 21, "size": 69}, {"id": 360, "name": "radialengine", "parent": 21, "size": 1}, {"id": 361, "name": "sandbag", "parent": 21, "size": 2}, {"id": 362, "name": "spaceheater", "parent": 21, "size": 1}, {"id": 363, "name": "system", "parent": 21, "size": 4}, {"id": 364, "name": "hotel", "parent": 21, "size": 1}, {"id": 365, "name": "webcam", "parent": 21, "size": 5}, {"id": 366, "name": "fabric", "parent": 21, "size": 2}, {"id": 367, "name": "modem", "parent": 21, "size": 9}, {"id": 368, "name": "harddisc", "parent": 21, "size": 3}, {"id": 369, "name": "horse", "parent": 21, "size": 18}, {"id": 370, "name": "chair", "parent": 21, "size": 307}, {"id": 371, "name": "kitchen", "parent": 21, "size": 3}, {"id": 372, "name": "exercisebike", "parent": 21, "size": 2}, {"id": 373, "name": "dumpster", "parent": 21, "size": 2}, {"id": 374, "name": "refriedbeans", "parent": 21, "size": 1}, {"id": 375, "name": "round-bottomflask", "parent": 21, "size": 1}, {"id": 376, "name": "marble", "parent": 21, "size": 1}, {"id": 377, "name": "series", "parent": 21, "size": 8}, {"id": 378, "name": "whiskey", "parent": 21, "size": 1}, {"id": 379, "name": "maverick", "parent": 21, "size": 1}, {"id": 380, "name": "shell", "parent": 21, "size": 3}, {"id": 381, "name": "gate", "parent": 21, "size": 3}, {"id": 382, "name": "footballhelmet", "parent": 21, "size": 4}, {"id": 383, "name": "excalibur", "parent": 21, "size": 1}, {"id": 384, "name": "van", "parent": 21, "size": 2}, {"id": 385, "name": "burner", "parent": 21, "size": 6}, {"id": 386, "name": "statue", "parent": 21, "size": 12}, {"id": 387, "name": "staplerwithstaples", "parent": 21, "size": 4}, {"id": 388, "name": "ballpark", "parent": 21, "size": 3}, {"id": 389, "name": "jersey", "parent": 21, "size": 1}, {"id": 390, "name": "internet", "parent": 21, "size": 2}, {"id": 391, "name": "battery", "parent": 21, "size": 20}, {"id": 392, "name": "saw", "parent": 21, "size": 2}, {"id": 393, "name": "pepsi", "parent": 21, "size": 3}, {"id": 394, "name": "tray", "parent": 21, "size": 9}, {"id": 395, "name": "soapbottle", "parent": 21, "size": 4}, {"id": 396, "name": "sponge", "parent": 21, "size": 1}, {"id": 397, "name": "singer", "parent": 21, "size": 1}, {"id": 398, "name": "salt", "parent": 21, "size": 2}, {"id": 399, "name": "antique", "parent": 21, "size": 2}, {"id": 400, "name": "workbench", "parent": 21, "size": 4}, {"id": 401, "name": "crossbow", "parent": 21, "size": 1}, {"id": 402, "name": "gingerbeer", "parent": 21, "size": 1}, {"id": 403, "name": "printer", "parent": 21, "size": 43}, {"id": 404, "name": "silo", "parent": 21, "size": 3}, {"id": 405, "name": "jet", "parent": 21, "size": 1}, {"id": 406, "name": "easel", "parent": 21, "size": 12}, {"id": 407, "name": "plate", "parent": 21, "size": 9}, {"id": 408, "name": "target", "parent": 21, "size": 10}, {"id": 409, "name": "drum", "parent": 21, "size": 4}, {"id": 410, "name": "jackdaw", "parent": 21, "size": 1}, {"id": 411, "name": "scene", "parent": 21, "size": 1}, {"id": 412, "name": "waterbottle", "parent": 21, "size": 1}, {"id": 413, "name": "bathroom", "parent": 21, "size": 2}, {"id": 414, "name": "richperson", "parent": 21, "size": 1}, {"id": 415, "name": "girl", "parent": 21, "size": 3}, {"id": 416, "name": "colt", "parent": 21, "size": 1}, {"id": 417, "name": "sharpener", "parent": 21, "size": 1}, {"id": 418, "name": "cap", "parent": 21, "size": 16}, {"id": 419, "name": "lighting", "parent": 21, "size": 1}, {"id": 420, "name": "spider", "parent": 21, "size": 2}, {"id": 421, "name": "toggleswitch", "parent": 21, "size": 1}, {"id": 422, "name": "towel", "parent": 21, "size": 3}, {"id": 423, "name": "dishwasher", "parent": 21, "size": 19}, {"id": 424, "name": "moon", "parent": 21, "size": 1}, {"id": 425, "name": "plunderer", "parent": 21, "size": 1}, {"id": 426, "name": "companion", "parent": 21, "size": 1}, {"id": 427, "name": "diesel", "parent": 21, "size": 1}, {"id": 428, "name": "lightingfixture", "parent": 21, "size": 1}, {"id": 429, "name": "hometheater", "parent": 21, "size": 1}, {"id": 430, "name": "fireplace", "parent": 21, "size": 38}, {"id": 431, "name": "hovercraft", "parent": 21, "size": 1}, {"id": 432, "name": "horselesscarriage", "parent": 21, "size": 1}, {"id": 433, "name": "atlas", "parent": 21, "size": 1}, {"id": 434, "name": "magnet", "parent": 21, "size": 8}, {"id": 435, "name": "toothpaste", "parent": 21, "size": 1}, {"id": 436, "name": "urinal", "parent": 21, "size": 3}, {"id": 437, "name": "coloringmaterial", "parent": 21, "size": 1}, {"id": 438, "name": "tube", "parent": 21, "size": 4}, {"id": 439, "name": "counter", "parent": 21, "size": 8}, {"id": 440, "name": "soapdish", "parent": 21, "size": 2}, {"id": 441, "name": "snowman", "parent": 21, "size": 8}, {"id": 442, "name": "diningtable", "parent": 21, "size": 91}, {"id": 443, "name": "beer", "parent": 21, "size": 1}, {"id": 444, "name": "guitar", "parent": 21, "size": 66}, {"id": 445, "name": "launcher", "parent": 21, "size": 5}, {"id": 446, "name": "walnut", "parent": 21, "size": 1}, {"id": 447, "name": "equipment", "parent": 21, "size": 6}, {"id": 448, "name": "futon", "parent": 21, "size": 2}, {"id": 449, "name": "chart", "parent": 21, "size": 1}, {"id": 450, "name": "pen", "parent": 21, "size": 32}, {"id": 451, "name": "samovar", "parent": 21, "size": 1}, {"id": 452, "name": "house", "parent": 21, "size": 3}, {"id": 453, "name": "straightener", "parent": 21, "size": 1}, {"id": 454, "name": "nest", "parent": 21, "size": 1}, {"id": 455, "name": "ammunition", "parent": 21, "size": 2}, {"id": 456, "name": "polaris", "parent": 21, "size": 1}, {"id": 457, "name": "pumpkin", "parent": 21, "size": 2}, {"id": 458, "name": "coathanger", "parent": 21, "size": 11}, {"id": 459, "name": "island", "parent": 21, "size": 2}, {"id": 460, "name": "form", "parent": 21, "size": 2}, {"id": 461, "name": "baby", "parent": 21, "size": 2}, {"id": 462, "name": "wallplate", "parent": 21, "size": 1}, {"id": 463, "name": "figurine", "parent": 21, "size": 1}, {"id": 464, "name": "lantern", "parent": 21, "size": 2}, {"id": 465, "name": "cigar", "parent": 21, "size": 3}, {"id": 466, "name": "device", "parent": 21, "size": 1}, {"id": 467, "name": "fixture", "parent": 21, "size": 1}, {"id": 468, "name": "maker", "parent": 21, "size": 1}, {"id": 469, "name": "spray", "parent": 21, "size": 2}, {"id": 470, "name": "mountainbike", "parent": 21, "size": 1}, {"id": 471, "name": "lego", "parent": 21, "size": 4}, {"id": 472, "name": "jigsawpuzzle", "parent": 21, "size": 1}, {"id": 473, "name": "radiobeacon", "parent": 21, "size": 1}, {"id": 474, "name": "cricketbat", "parent": 21, "size": 3}, {"id": 475, "name": "picnictableset", "parent": 21, "size": 3}, {"id": 476, "name": "clorox", "parent": 21, "size": 1}, {"id": 477, "name": "colossus", "parent": 21, "size": 1}, {"id": 478, "name": "plaque", "parent": 21, "size": 3}, {"id": 479, "name": "stallion", "parent": 21, "size": 1}, {"id": 480, "name": "router", "parent": 21, "size": 5}, {"id": 481, "name": "porcupine", "parent": 21, "size": 3}, {"id": 482, "name": "egg", "parent": 21, "size": 2}, {"id": 483, "name": "ark", "parent": 21, "size": 1}, {"id": 484, "name": "maze", "parent": 21, "size": 2}, {"id": 485, "name": "sculpture", "parent": 21, "size": 6}, {"id": 486, "name": "knife", "parent": 21, "size": 32}, {"id": 487, "name": "pill", "parent": 21, "size": 2}, {"id": 488, "name": "fire", "parent": 21, "size": 2}, {"id": 489, "name": "tool", "parent": 21, "size": 3}, {"id": 490, "name": "cashmachine", "parent": 21, "size": 1}, {"id": 491, "name": "lamp", "parent": 21, "size": 35}, {"id": 492, "name": "microphone", "parent": 21, "size": 5}, {"id": 493, "name": "bullet", "parent": 21, "size": 2}, {"id": 494, "name": "matrix", "parent": 21, "size": 1}, {"id": 495, "name": "mailbox", "parent": 21, "size": 2}, {"id": 496, "name": "cage", "parent": 21, "size": 11}, {"id": 497, "name": "ipad", "parent": 21, "size": 2}, {"id": 498, "name": "lecorbusier", "parent": 21, "size": 1}, {"id": 499, "name": "militaryofficer", "parent": 21, "size": 1}, {"id": 500, "name": "frog", "parent": 21, "size": 2}, {"id": 501, "name": "tumbler", "parent": 21, "size": 2}, {"id": 502, "name": "pole", "parent": 21, "size": 1}, {"id": 503, "name": "chili", "parent": 21, "size": 1}, {"id": 504, "name": "erlenmeyerflask", "parent": 21, "size": 1}, {"id": 505, "name": "bulb", "parent": 21, "size": 1}, {"id": 506, "name": "vehicle", "parent": 21, "size": 1}, {"id": 507, "name": "bob", "parent": 21, "size": 1}, {"id": 508, "name": "cellulartelephone", "parent": 21, "size": 1}, {"id": 509, "name": "killerwhale", "parent": 21, "size": 1}, {"id": 510, "name": "block", "parent": 21, "size": 1}, {"id": 511, "name": "yttrium", "parent": 21, "size": 2}, {"id": 512, "name": "oil", "parent": 21, "size": 1}, {"id": 513, "name": "self", "parent": 21, "size": 1}, {"id": 514, "name": "cruiser", "parent": 21, "size": 1}, {"id": 515, "name": "spring", "parent": 21, "size": 1}, {"id": 516, "name": "ponytail", "parent": 21, "size": 1}, {"id": 517, "name": "chestofdrawers", "parent": 21, "size": 144}, {"id": 518, "name": "generator", "parent": 21, "size": 1}, {"id": 519, "name": "android", "parent": 21, "size": 2}, {"id": 520, "name": "interiordesigner", "parent": 21, "size": 2}, {"id": 521, "name": "molding", "parent": 21, "size": 1}, {"id": 522, "name": "display", "parent": 21, "size": 2}, {"id": 523, "name": "booklet", "parent": 21, "size": 3}, {"id": 524, "name": "televisioncamera", "parent": 21, "size": 1}, {"id": 525, "name": "hanging", "parent": 21, "size": 1}, {"id": 526, "name": "sword", "parent": 21, "size": 39}, {"id": 527, "name": "backpack", "parent": 21, "size": 5}, {"id": 528, "name": "videodisk", "parent": 21, "size": 8}, {"id": 529, "name": "tire", "parent": 21, "size": 1}, {"id": 530, "name": "walker", "parent": 21, "size": 1}, {"id": 531, "name": "microwave", "parent": 21, "size": 24}, {"id": 532, "name": "diner", "parent": 21, "size": 1}, {"id": 533, "name": "jackfruit", "parent": 21, "size": 2}, {"id": 534, "name": "monitor", "parent": 21, "size": 124}, {"id": 535, "name": "stick", "parent": 21, "size": 1}, {"id": 536, "name": "onyx", "parent": 21, "size": 1}, {"id": 537, "name": "kleenex", "parent": 21, "size": 1}, {"id": 538, "name": "hygrometer", "parent": 21, "size": 1}, {"id": 539, "name": "filing", "parent": 21, "size": 1}, {"id": 540, "name": "elgreco", "parent": 21, "size": 1}, {"id": 541, "name": "part", "parent": 21, "size": 4}, {"id": 542, "name": "kit", "parent": 21, "size": 3}, {"id": 543, "name": "banana", "parent": 21, "size": 10}, {"id": 544, "name": "basic", "parent": 21, "size": 1}, {"id": 545, "name": "washerdryerset", "parent": 21, "size": 7}, {"id": 546, "name": "coffeetable", "parent": 21, "size": 82}, {"id": 547, "name": "bathtub", "parent": 21, "size": 22}, {"id": 548, "name": "toiletroll", "parent": 21, "size": 1}, {"id": 549, "name": "caribou", "parent": 21, "size": 1}, {"id": 550, "name": "horn", "parent": 21, "size": 1}, {"id": 551, "name": "spicerack", "parent": 21, "size": 1}, {"id": 552, "name": "parasite", "parent": 21, "size": 1}, {"id": 553, "name": "stainlesssteel", "parent": 21, "size": 1}, {"id": 554, "name": "guard", "parent": 21, "size": 3}, {"id": 555, "name": "tourist", "parent": 21, "size": 1}, {"id": 556, "name": "mat", "parent": 21, "size": 1}, {"id": 557, "name": "clothing", "parent": 21, "size": 1}, {"id": 558, "name": "dial", "parent": 21, "size": 1}, {"id": 559, "name": "fruit", "parent": 21, "size": 5}, {"id": 560, "name": "pencilbox", "parent": 21, "size": 1}, {"id": 561, "name": "adjustablewrench", "parent": 21, "size": 1}, {"id": 562, "name": "candlestick", "parent": 21, "size": 2}, {"id": 563, "name": "spacecraft", "parent": 21, "size": 1}, {"id": 564, "name": "technology", "parent": 21, "size": 1}, {"id": 565, "name": "blackboard", "parent": 21, "size": 4}, {"id": 566, "name": "greek", "parent": 21, "size": 1}, {"id": 567, "name": "clock", "parent": 21, "size": 91}, {"id": 568, "name": "tape", "parent": 21, "size": 5}, {"id": 569, "name": "issue", "parent": 21, "size": 3}, {"id": 570, "name": "terry", "parent": 21, "size": 1}, {"id": 571, "name": "mongoose", "parent": 21, "size": 1}, {"id": 572, "name": "watercooler", "parent": 21, "size": 1}, {"id": 573, "name": "food", "parent": 21, "size": 2}, {"id": 574, "name": "facsimile", "parent": 21, "size": 1}, {"id": 575, "name": "cesium", "parent": 21, "size": 1}, {"id": 576, "name": "cookie", "parent": 21, "size": 6}, {"id": 577, "name": "napkin", "parent": 21, "size": 1}, {"id": 578, "name": "octopus", "parent": 21, "size": 2}, {"id": 579, "name": "icelolly", "parent": 21, "size": 2}, {"id": 580, "name": "morion", "parent": 21, "size": 1}, {"id": 581, "name": "bag", "parent": 21, "size": 11}, {"id": 582, "name": "computer", "parent": 21, "size": 9}, {"id": 583, "name": "mod", "parent": 21, "size": 1}, {"id": 584, "name": "bumblebee", "parent": 21, "size": 1}, {"id": 585, "name": "tractor", "parent": 21, "size": 3}, {"id": 586, "name": "bot", "parent": 21, "size": 1}, {"id": 587, "name": "bible", "parent": 21, "size": 1}, {"id": 588, "name": "apprentice", "parent": 21, "size": 1}, {"id": 589, "name": "ara", "parent": 21, "size": 1}, {"id": 590, "name": "chino", "parent": 21, "size": 2}, {"id": 591, "name": "handglass", "parent": 21, "size": 1}, {"id": 592, "name": "caseshot", "parent": 21, "size": 1}, {"id": 593, "name": "kennel", "parent": 21, "size": 1}, {"id": 594, "name": "sign", "parent": 21, "size": 3}, {"id": 595, "name": "hart", "parent": 21, "size": 2}, {"id": 596, "name": "hotplate", "parent": 21, "size": 2}, {"id": 597, "name": "pyramid", "parent": 21, "size": 1}, {"id": 598, "name": "fortress", "parent": 21, "size": 2}, {"id": 599, "name": "snail", "parent": 21, "size": 1}, {"id": 600, "name": "placesetting", "parent": 21, "size": 2}, {"id": 601, "name": "heart", "parent": 21, "size": 1}, {"id": 602, "name": "striker", "parent": 21, "size": 1}, {"id": 603, "name": "chineselantern", "parent": 21, "size": 3}, {"id": 604, "name": "weight", "parent": 21, "size": 3}, {"id": 605, "name": "ribbon", "parent": 21, "size": 1}, {"id": 606, "name": "armor", "parent": 21, "size": 2}, {"id": 607, "name": "americanflag", "parent": 21, "size": 1}, {"id": 608, "name": "adam", "parent": 21, "size": 2}, {"id": 609, "name": "chandelier", "parent": 21, "size": 2}, {"id": 610, "name": "starship", "parent": 21, "size": 2}, {"id": 611, "name": "monkey", "parent": 21, "size": 1}, {"id": 612, "name": "sphere", "parent": 21, "size": 2}, {"id": 613, "name": "musicstand", "parent": 21, "size": 2}, {"id": 614, "name": "friend", "parent": 21, "size": 1}, {"id": 615, "name": "gas", "parent": 21, "size": 1}, {"id": 616, "name": "ambulance", "parent": 21, "size": 1}, {"id": 617, "name": "tent", "parent": 21, "size": 3}, {"id": 618, "name": "crystal", "parent": 21, "size": 3}, {"id": 619, "name": "gorilla", "parent": 21, "size": 1}, {"id": 620, "name": "quilt", "parent": 21, "size": 1}, {"id": 621, "name": "ray", "parent": 21, "size": 1}, {"id": 622, "name": "adenosinedeaminase", "parent": 21, "size": 2}, {"id": 623, "name": "sprinter", "parent": 21, "size": 1}, {"id": 624, "name": "sheet", "parent": 21, "size": 1}, {"id": 625, "name": "palette", "parent": 21, "size": 2}, {"id": 626, "name": "professional", "parent": 21, "size": 1}, {"id": 627, "name": "solubleglass", "parent": 21, "size": 1}, {"id": 628, "name": "platter", "parent": 21, "size": 2}, {"id": 629, "name": "module", "parent": 21, "size": 1}, {"id": 630, "name": "centralprocessingunit", "parent": 21, "size": 3}, {"id": 631, "name": "directionalmicrophone", "parent": 21, "size": 1}, {"id": 632, "name": "acetylene", "parent": 21, "size": 1}, {"id": 633, "name": "container", "parent": 21, "size": 5}, {"id": 634, "name": "gateway", "parent": 21, "size": 1}, {"id": 635, "name": "hog", "parent": 21, "size": 2}, {"id": 636, "name": "humvee", "parent": 21, "size": 2}, {"id": 637, "name": "passengercar", "parent": 21, "size": 1}, {"id": 638, "name": "cartridgeholder", "parent": 21, "size": 3}, {"id": 639, "name": "gastank", "parent": 21, "size": 1}, {"id": 640, "name": "iodine", "parent": 21, "size": 1}, {"id": 641, "name": "harvester", "parent": 21, "size": 1}, {"id": 642, "name": "corbel", "parent": 21, "size": 1}, {"id": 643, "name": "arrow", "parent": 21, "size": 3}, {"id": 644, "name": "drywall", "parent": 21, "size": 1}, {"id": 645, "name": "frisbee", "parent": 21, "size": 1}, {"id": 646, "name": "surface", "parent": 21, "size": 2}, {"id": 647, "name": "ballandchain", "parent": 21, "size": 1}, {"id": 648, "name": "jig", "parent": 21, "size": 1}, {"id": 649, "name": "shellfish", "parent": 21, "size": 1}, {"id": 650, "name": "drew", "parent": 21, "size": 1}, {"id": 651, "name": "shield", "parent": 21, "size": 1}, {"id": 652, "name": "menu", "parent": 21, "size": 1}, {"id": 653, "name": "drinkingfountain", "parent": 21, "size": 1}, {"id": 654, "name": "socketwrench", "parent": 21, "size": 2}, {"id": 655, "name": "tank", "parent": 21, "size": 14}, {"id": 656, "name": "assaultrifle", "parent": 21, "size": 1}, {"id": 657, "name": "butterfly", "parent": 21, "size": 2}, {"id": 658, "name": "merchandise", "parent": 21, "size": 1}, {"id": 659, "name": "santaclaus", "parent": 21, "size": 1}, {"id": 660, "name": "wheelchair", "parent": 21, "size": 1}, {"id": 661, "name": "claymore", "parent": 21, "size": 1}, {"id": 662, "name": "towelrail", "parent": 21, "size": 4}, {"id": 663, "name": "vancouver", "parent": 21, "size": 1}, {"id": 664, "name": "mosaicgold", "parent": 21, "size": 1}, {"id": 665, "name": "filter", "parent": 21, "size": 1}, {"id": 666, "name": "knot", "parent": 21, "size": 1}, {"id": 667, "name": "windmill", "parent": 21, "size": 1}, {"id": 668, "name": "heatingsystem", "parent": 21, "size": 1}, {"id": 669, "name": "mate", "parent": 21, "size": 1}, {"id": 670, "name": "winder", "parent": 21, "size": 1}, {"id": 671, "name": "mirror", "parent": 21, "size": 26}, {"id": 672, "name": "shaker", "parent": 21, "size": 2}, {"id": 673, "name": "garbage", "parent": 21, "size": 1}, {"id": 674, "name": "roller", "parent": 21, "size": 1}, {"id": 675, "name": "pushbroom", "parent": 21, "size": 1}, {"id": 676, "name": "notebook", "parent": 21, "size": 1}, {"id": 677, "name": "sky", "parent": 21, "size": 1}, {"id": 678, "name": "coke", "parent": 21, "size": 1}, {"id": 679, "name": "balloon", "parent": 21, "size": 1}, {"id": 680, "name": "spatula", "parent": 21, "size": 2}, {"id": 681, "name": "plaything", "parent": 21, "size": 1}, {"id": 682, "name": "missile", "parent": 21, "size": 3}, {"id": 683, "name": "powershovel", "parent": 21, "size": 1}, {"id": 684, "name": "plan", "parent": 21, "size": 1}, {"id": 685, "name": "interiordecoration", "parent": 21, "size": 2}, {"id": 686, "name": "kiln", "parent": 21, "size": 1}, {"id": 687, "name": "teaservice", "parent": 21, "size": 2}, {"id": 688, "name": "brush", "parent": 21, "size": 2}, {"id": 689, "name": "shockabsorber", "parent": 21, "size": 1}, {"id": 690, "name": "chessman", "parent": 21, "size": 1}, {"id": 691, "name": "saucepan", "parent": 21, "size": 2}, {"id": 692, "name": "fiddlestick", "parent": 21, "size": 1}, {"id": 693, "name": "skater", "parent": 21, "size": 1}, {"id": 694, "name": "toothpick", "parent": 21, "size": 1}, {"id": 695, "name": "airship", "parent": 21, "size": 3}, {"id": 696, "name": "toybox", "parent": 21, "size": 1}, {"id": 697, "name": "assassin", "parent": 21, "size": 1}, {"id": 698, "name": "base", "parent": 21, "size": 2}, {"id": 699, "name": "stove", "parent": 21, "size": 3}, {"id": 700, "name": "padlock", "parent": 21, "size": 1}, {"id": 701, "name": "cable", "parent": 21, "size": 1}, {"id": 702, "name": "insect", "parent": 21, "size": 1}, {"id": 703, "name": "barrack", "parent": 21, "size": 1}, {"id": 704, "name": "grill", "parent": 21, "size": 1}, {"id": 705, "name": "vacuum", "parent": 21, "size": 3}, {"id": 706, "name": "martini", "parent": 21, "size": 1}, {"id": 707, "name": "vacuumflask", "parent": 21, "size": 1}, {"id": 708, "name": "shirt", "parent": 21, "size": 14}, {"id": 709, "name": "attacker", "parent": 21, "size": 1}, {"id": 710, "name": "weapon", "parent": 21, "size": 2}, {"id": 711, "name": "robe", "parent": 21, "size": 1}, {"id": 712, "name": "thermostat", "parent": 21, "size": 3}, {"id": 713, "name": "pentobarbitalsodium", "parent": 21, "size": 1}, {"id": 714, "name": "bean", "parent": 21, "size": 1}, {"id": 715, "name": "belt", "parent": 21, "size": 1}, {"id": 716, "name": "canopy", "parent": 21, "size": 3}, {"id": 717, "name": "socket", "parent": 21, "size": 1}, {"id": 718, "name": "school", "parent": 21, "size": 2}, {"id": 719, "name": "towelrack", "parent": 21, "size": 2}, {"id": 720, "name": "post-it", "parent": 21, "size": 1}, {"id": 721, "name": "ironingboard", "parent": 21, "size": 2}, {"id": 722, "name": "storehouse", "parent": 21, "size": 1}, {"id": 723, "name": "log", "parent": 21, "size": 1}, {"id": 724, "name": "variation", "parent": 21, "size": 1}, {"id": 725, "name": "deodorant", "parent": 21, "size": 1}, {"id": 726, "name": "black", "parent": 21, "size": 1}, {"id": 727, "name": "sea", "parent": 21, "size": 1}, {"id": 728, "name": "armyant", "parent": 21, "size": 1}, {"id": 729, "name": "birdfeeder", "parent": 21, "size": 1}, {"id": 730, "name": "aurochs", "parent": 21, "size": 1}, {"id": 731, "name": "braun", "parent": 21, "size": 1}, {"id": 732, "name": "shot", "parent": 21, "size": 1}, {"id": 733, "name": "beerbottle", "parent": 21, "size": 13}, {"id": 734, "name": "adenosinemonophosphate", "parent": 21, "size": 1}, {"id": 735, "name": "artillery", "parent": 21, "size": 1}, {"id": 736, "name": "bug", "parent": 21, "size": 2}, {"id": 737, "name": "tennisracket", "parent": 21, "size": 2}, {"id": 738, "name": "slot", "parent": 21, "size": 1}, {"id": 739, "name": "room", "parent": 21, "size": 3}, {"id": 740, "name": "shelter", "parent": 21, "size": 1}, {"id": 741, "name": "bunsenburner", "parent": 21, "size": 1}, {"id": 742, "name": "pommel", "parent": 21, "size": 1}, {"id": 743, "name": "crap", "parent": 21, "size": 1}, {"id": 744, "name": "component", "parent": 21, "size": 3}, {"id": 745, "name": "statueofliberty", "parent": 21, "size": 1}, {"id": 746, "name": "stool", "parent": 21, "size": 28}, {"id": 747, "name": "keyboard", "parent": 21, "size": 20}, {"id": 748, "name": "crusader", "parent": 21, "size": 1}, {"id": 749, "name": "acetaminophen", "parent": 21, "size": 1}, {"id": 750, "name": "raft", "parent": 21, "size": 1}, {"id": 751, "name": "toast", "parent": 21, "size": 2}, {"id": 752, "name": "remotecontrol", "parent": 21, "size": 1}, {"id": 753, "name": "mine", "parent": 21, "size": 1}, {"id": 754, "name": "bat", "parent": 21, "size": 3}, {"id": 755, "name": "table-tennistable", "parent": 21, "size": 1}, {"id": 756, "name": "batman", "parent": 21, "size": 1}, {"id": 757, "name": "chain", "parent": 21, "size": 1}, {"id": 758, "name": "parkingmeter", "parent": 21, "size": 1}, {"id": 759, "name": "taco", "parent": 21, "size": 1}, {"id": 760, "name": "thrall", "parent": 21, "size": 1}, {"id": 761, "name": "makeup", "parent": 21, "size": 1}, {"id": 762, "name": "alcohol", "parent": 21, "size": 1}, {"id": 763, "name": "leaf", "parent": 21, "size": 1}, {"id": 764, "name": "drink", "parent": 21, "size": 1}, {"id": 765, "name": "goal", "parent": 21, "size": 2}, {"id": 766, "name": "grocerystore", "parent": 21, "size": 2}, {"id": 767, "name": "person", "parent": 21, "size": 1}, {"id": 768, "name": "bassdrum", "parent": 21, "size": 2}, {"id": 769, "name": "commander", "parent": 21, "size": 1}, {"id": 770, "name": "castiron", "parent": 21, "size": 1}, {"id": 771, "name": "pipe", "parent": 21, "size": 1}, {"id": 772, "name": "nitrogen", "parent": 21, "size": 1}, {"id": 773, "name": "easychair", "parent": 21, "size": 1}, {"id": 774, "name": "biplane", "parent": 21, "size": 1}, {"id": 775, "name": "fly", "parent": 21, "size": 1}, {"id": 776, "name": "helicopter", "parent": 21, "size": 23}, {"id": 777, "name": "cab", "parent": 21, "size": 1}, {"id": 778, "name": "trimming", "parent": 21, "size": 1}, {"id": 779, "name": "televisionreceiver", "parent": 21, "size": 1}, {"id": 780, "name": "basketball", "parent": 21, "size": 1}, {"id": 781, "name": "punchpress", "parent": 21, "size": 1}, {"id": 782, "name": "mobiusstrip", "parent": 21, "size": 1}, {"id": 783, "name": "bed", "parent": 21, "size": 7}, {"id": 784, "name": "terminal", "parent": 21, "size": 1}, {"id": 785, "name": "core", "parent": 21, "size": 1}, {"id": 786, "name": "hand", "parent": 21, "size": 1}, {"id": 787, "name": "naturalgas", "parent": 21, "size": 3}, {"id": 788, "name": "scale", "parent": 21, "size": 2}, {"id": 789, "name": "sheetmetal", "parent": 21, "size": 1}, {"id": 790, "name": "coin", "parent": 21, "size": 6}, {"id": 791, "name": "taperecorder", "parent": 21, "size": 1}, {"id": 792, "name": "haybale", "parent": 21, "size": 1}, {"id": 793, "name": "telephone", "parent": 21, "size": 39}, {"id": 794, "name": "church", "parent": 21, "size": 1}, {"id": 795, "name": "weed", "parent": 21, "size": 1}, {"id": 796, "name": "architeuthis", "parent": 21, "size": 1}, {"id": 797, "name": "xerox", "parent": 21, "size": 1}, {"id": 798, "name": "swing", "parent": 21, "size": 1}, {"id": 799, "name": "aquarium", "parent": 21, "size": 1}, {"id": 800, "name": "panel", "parent": 21, "size": 1}, {"id": 801, "name": "espresso", "parent": 21, "size": 1}, {"id": 802, "name": "waste", "parent": 21, "size": 1}, {"id": 803, "name": "dress", "parent": 21, "size": 1}, {"id": 804, "name": "troopcarrier", "parent": 21, "size": 2}, {"id": 805, "name": "metallicelement", "parent": 21, "size": 1}, {"id": 806, "name": "avenger", "parent": 21, "size": 1}, {"id": 807, "name": "file", "parent": 21, "size": 1}, {"id": 808, "name": "animal", "parent": 21, "size": 2}, {"id": 809, "name": "soysauce", "parent": 21, "size": 1}, {"id": 810, "name": "rocket", "parent": 21, "size": 3}, {"id": 811, "name": "soccerball", "parent": 21, "size": 1}, {"id": 812, "name": "newton", "parent": 21, "size": 1}, {"id": 813, "name": "tea", "parent": 21, "size": 2}, {"id": 814, "name": "recycling", "parent": 21, "size": 1}, {"id": 815, "name": "personaldigitalassistant", "parent": 21, "size": 1}, {"id": 816, "name": "glass", "parent": 21, "size": 3}, {"id": 817, "name": "donkey", "parent": 21, "size": 1}, {"id": 818, "name": "keeper", "parent": 21, "size": 1}, {"id": 819, "name": "wallartwithfigurine", "parent": 21, "size": 2}, {"id": 820, "name": "chip", "parent": 21, "size": 1}, {"id": 821, "name": "banquette", "parent": 21, "size": 1}, {"id": 822, "name": "phosphorus", "parent": 21, "size": 1}, {"id": 823, "name": "burlap", "parent": 21, "size": 1}, {"id": 824, "name": "palace", "parent": 21, "size": 1}, {"id": 825, "name": "neckpiece", "parent": 21, "size": 1}, {"id": 826, "name": "mariner", "parent": 21, "size": 1}, {"id": 827, "name": "bric-a-brac", "parent": 21, "size": 1}, {"id": 828, "name": "wrestlingring", "parent": 21, "size": 1}, {"id": 829, "name": "barrier", "parent": 21, "size": 1}, {"id": 830, "name": "pooltable", "parent": 21, "size": 1}, {"id": 831, "name": "igniter", "parent": 21, "size": 1}, {"id": 832, "name": "guy", "parent": 21, "size": 1}, {"id": 833, "name": "roman", "parent": 21, "size": 1}, {"id": 834, "name": "jello", "parent": 21, "size": 1}, {"id": 835, "name": "bloomers", "parent": 21, "size": 2}, {"id": 836, "name": "craft", "parent": 21, "size": 1}, {"id": 837, "name": "bunker", "parent": 21, "size": 1}, {"id": 838, "name": "turntable", "parent": 21, "size": 1}, {"id": 839, "name": "shoppingcart", "parent": 21, "size": 2}, {"id": 840, "name": "defender", "parent": 21, "size": 1}, {"id": 841, "name": "plow", "parent": 21, "size": 1}, {"id": 842, "name": "engagementring", "parent": 21, "size": 1}, {"id": 843, "name": "frenchfries", "parent": 21, "size": 1}, {"id": 844, "name": "chow", "parent": 21, "size": 1}, {"id": 845, "name": "stable", "parent": 21, "size": 1}, {"id": 846, "name": "voyager", "parent": 21, "size": 2}, {"id": 847, "name": "defensivestructure", "parent": 21, "size": 2}, {"id": 848, "name": "cover", "parent": 21, "size": 1}, {"id": 849, "name": "engineblock", "parent": 21, "size": 1}, {"id": 850, "name": "range", "parent": 21, "size": 1}, {"id": 851, "name": "coatrack", "parent": 21, "size": 18}, {"id": 852, "name": "flatware", "parent": 21, "size": 1}, {"id": 853, "name": "sherman", "parent": 21, "size": 1}, {"id": 854, "name": "rubbish", "parent": 21, "size": 1}, {"id": 855, "name": "doughboy", "parent": 21, "size": 1}, {"id": 856, "name": "library", "parent": 21, "size": 1}, {"id": 857, "name": "pack", "parent": 21, "size": 1}, {"id": 858, "name": "highgear", "parent": 21, "size": 1}, {"id": 859, "name": "guitarist", "parent": 21, "size": 1}, {"id": 860, "name": "pop", "parent": 21, "size": 1}, {"id": 861, "name": "roulettewheel", "parent": 21, "size": 1}, {"id": 862, "name": "bagel", "parent": 21, "size": 1}, {"id": 863, "name": "mantel", "parent": 21, "size": 1}, {"id": 864, "name": "apparatus", "parent": 21, "size": 1}, {"id": 865, "name": "receiver", "parent": 21, "size": 4}, {"id": 866, "name": "flower", "parent": 21, "size": 2}, {"id": 867, "name": "theater", "parent": 21, "size": 1}, {"id": 868, "name": "unit", "parent": 21, "size": 3}, {"id": 869, "name": "cassetterecorder", "parent": 21, "size": 1}, {"id": 870, "name": "assault", "parent": 21, "size": 1}, {"id": 871, "name": "tuna", "parent": 21, "size": 1}, {"id": 872, "name": "onion", "parent": 21, "size": 1}, {"id": 873, "name": "aircraftcarrier", "parent": 21, "size": 1}, {"id": 874, "name": "office", "parent": 21, "size": 1}, {"id": 875, "name": "piggybank", "parent": 21, "size": 1}, {"id": 876, "name": "firstclass", "parent": 21, "size": 1}, {"id": 877, "name": "pallet", "parent": 21, "size": 1}, {"id": 878, "name": "oniondome", "parent": 21, "size": 1}, {"id": 879, "name": "furniture", "parent": 21, "size": 2}, {"id": 880, "name": "cosmetic", "parent": 21, "size": 1}, {"id": 881, "name": "formalwear", "parent": 21, "size": 1}, {"id": 882, "name": "bud", "parent": 21, "size": 1}, {"id": 883, "name": "controlpanel", "parent": 21, "size": 1}, {"id": 884, "name": "maple", "parent": 21, "size": 1}, {"id": 885, "name": "tapestry", "parent": 21, "size": 1}, {"id": 886, "name": "mare", "parent": 21, "size": 1}, {"id": 887, "name": "deep-freeze", "parent": 21, "size": 2}, {"id": 888, "name": "train", "parent": 21, "size": 1}, {"id": 889, "name": "hanger", "parent": 21, "size": 7}, {"id": 890, "name": "group", "parent": 21, "size": 1}, {"id": 891, "name": "griddle", "parent": 21, "size": 1}, {"id": 892, "name": "baronet", "parent": 21, "size": 1}, {"id": 893, "name": "cornet", "parent": 21, "size": 1}, {"id": 894, "name": "hotpot", "parent": 21, "size": 1}, {"id": 895, "name": "monkey-wrench", "parent": 21, "size": 1}, {"id": 896, "name": "cosmopolitan", "parent": 21, "size": 1}, {"id": 897, "name": "football", "parent": 21, "size": 1}, {"id": 898, "name": "baluster", "parent": 21, "size": 1}, {"id": 899, "name": "negligee", "parent": 21, "size": 1}, {"id": 900, "name": "causeofdeath", "parent": 21, "size": 1}, {"id": 901, "name": "sink", "parent": 21, "size": 39}, {"id": 902, "name": "nail", "parent": 21, "size": 1}, {"id": 903, "name": "mace", "parent": 21, "size": 1}, {"id": 904, "name": "oak", "parent": 21, "size": 1}, {"id": 905, "name": "potter", "parent": 21, "size": 1}, {"id": 906, "name": "bunkbed", "parent": 21, "size": 1}, {"id": 907, "name": "writingdesk", "parent": 21, "size": 1}, {"id": 908, "name": "baseballbat", "parent": 21, "size": 3}, {"id": 909, "name": "defensesystem", "parent": 21, "size": 1}, {"id": 910, "name": "sushi", "parent": 21, "size": 1}, {"id": 911, "name": "chickenfeed", "parent": 21, "size": 1}, {"id": 912, "name": "paddle", "parent": 21, "size": 1}, {"id": 913, "name": "soffit", "parent": 21, "size": 1}, {"id": 914, "name": "power", "parent": 21, "size": 1}, {"id": 915, "name": "tablet", "parent": 21, "size": 1}, {"id": 916, "name": "probe", "parent": 21, "size": 1}, {"id": 917, "name": "tricycle", "parent": 21, "size": 1}, {"id": 918, "name": "automation", "parent": 21, "size": 1}, {"id": 919, "name": "joint", "parent": 21, "size": 1}, {"id": 920, "name": "couple", "parent": 21, "size": 1}, {"id": 921, "name": "bath", "parent": 21, "size": 1}, {"id": 922, "name": "binder", "parent": 21, "size": 1}, {"id": 923, "name": "skeleton", "parent": 21, "size": 1}, {"id": 924, "name": "silicon", "parent": 21, "size": 1}, {"id": 925, "name": "bobbin", "parent": 21, "size": 2}, {"id": 926, "name": "die", "parent": 21, "size": 2}, {"id": 927, "name": "projection", "parent": 21, "size": 1}, {"id": 928, "name": "trampoline", "parent": 21, "size": 1}, {"id": 929, "name": "manual", "parent": 21, "size": 1}, {"id": 930, "name": "crossing", "parent": 21, "size": 1}, {"id": 931, "name": "mouser", "parent": 21, "size": 1}, {"id": 932, "name": "typewriter", "parent": 21, "size": 1}, {"id": 933, "name": "punch", "parent": 21, "size": 1}, {"id": 934, "name": "prostatespecificantigen", "parent": 21, "size": 1}, {"id": 935, "name": "participant", "parent": 21, "size": 1}, {"id": 936, "name": "cdplayer", "parent": 21, "size": 1}, {"id": 937, "name": "portrait", "parent": 21, "size": 1}, {"id": 938, "name": "butt", "parent": 21, "size": 2}, {"id": 939, "name": "trellis", "parent": 21, "size": 1}, {"id": 940, "name": "beam", "parent": 21, "size": 1}, {"id": 941, "name": "slideprojector", "parent": 21, "size": 1}, {"id": 942, "name": "bow", "parent": 21, "size": 1}, {"id": 943, "name": "icemaker", "parent": 21, "size": 1}, {"id": 944, "name": "book", "parent": 21, "size": 72}, {"id": 945, "name": "piece", "parent": 21, "size": 1}, {"id": 946, "name": "section", "parent": 21, "size": 1}, {"id": 947, "name": "butcherknife", "parent": 21, "size": 1}, {"id": 948, "name": "bender", "parent": 21, "size": 1}, {"id": 949, "name": "addingmachine", "parent": 21, "size": 1}, {"id": 950, "name": "icecream", "parent": 21, "size": 1}, {"id": 951, "name": "donna", "parent": 21, "size": 1}, {"id": 952, "name": "trumpet", "parent": 21, "size": 1}, {"id": 953, "name": "hospital", "parent": 21, "size": 1}, {"id": 954, "name": "stethoscope", "parent": 21, "size": 1}, {"id": 955, "name": "ice", "parent": 21, "size": 1}, {"id": 956, "name": "lancer", "parent": 21, "size": 1}, {"id": 957, "name": "exhaustfan", "parent": 21, "size": 1}, {"id": 958, "name": "umbrella", "parent": 21, "size": 18}, {"id": 959, "name": "christmasstocking", "parent": 21, "size": 1}, {"id": 960, "name": "ratchet", "parent": 21, "size": 1}, {"id": 961, "name": "awning", "parent": 21, "size": 1}, {"id": 962, "name": "embodiment", "parent": 21, "size": 1}, {"id": 963, "name": "jaguar", "parent": 21, "size": 1}, {"id": 964, "name": "workbook", "parent": 21, "size": 1}, {"id": 965, "name": "photocopier", "parent": 21, "size": 1}, {"id": 966, "name": "railing", "parent": 21, "size": 1}, {"id": 967, "name": "trail", "parent": 21, "size": 1}, {"id": 968, "name": "tender", "parent": 21, "size": 1}, {"id": 969, "name": "caisson", "parent": 21, "size": 1}, {"id": 970, "name": "hole", "parent": 21, "size": 1}, {"id": 971, "name": "chess", "parent": 21, "size": 1}, {"id": 972, "name": "pan", "parent": 21, "size": 19}, {"id": 973, "name": "wallsocket", "parent": 21, "size": 1}, {"id": 974, "name": "window", "parent": 21, "size": 10}, {"id": 975, "name": "adapter", "parent": 21, "size": 1}, {"id": 976, "name": "waterwheel", "parent": 21, "size": 1}, {"id": 977, "name": "portal", "parent": 21, "size": 1}, {"id": 978, "name": "handbrake", "parent": 21, "size": 1}, {"id": 979, "name": "scythe", "parent": 21, "size": 1}, {"id": 980, "name": "launch", "parent": 21, "size": 1}, {"id": 981, "name": "puzzle", "parent": 21, "size": 1}, {"id": 982, "name": "hangglider", "parent": 21, "size": 1}, {"id": 983, "name": "area", "parent": 21, "size": 1}, {"id": 984, "name": "paint", "parent": 21, "size": 1}, {"id": 985, "name": "spice", "parent": 21, "size": 1}, {"id": 986, "name": "timemachine", "parent": 21, "size": 1}, {"id": 987, "name": "bin", "parent": 21, "size": 1}, {"id": 988, "name": "bigcat", "parent": 21, "size": 1}, {"id": 989, "name": "rubber", "parent": 21, "size": 1}, {"id": 990, "name": "down", "parent": 21, "size": 1}, {"id": 991, "name": "doughnut", "parent": 21, "size": 1}, {"id": 992, "name": "drugstore", "parent": 21, "size": 1}, {"id": 993, "name": "alarm", "parent": 21, "size": 1}, {"id": 994, "name": "personalcomputer", "parent": 21, "size": 1}, {"id": 995, "name": "sum", "parent": 21, "size": 1}, {"id": 996, "name": "waterscooter", "parent": 21, "size": 1}, {"id": 997, "name": "spiral", "parent": 21, "size": 1}, {"id": 998, "name": "seabass", "parent": 21, "size": 1}, {"id": 999, "name": "master", "parent": 21, "size": 1}, {"id": 1000, "name": "kleinbottle", "parent": 21, "size": 1}, {"id": 1001, "name": "nailpolish", "parent": 21, "size": 1}, {"id": 1002, "name": "mayan", "parent": 21, "size": 1}, {"id": 1003, "name": "hornet", "parent": 21, "size": 1}, {"id": 1004, "name": "chestofdrawers", "parent": 1}, {"id": 1005, "name": "dresserwithmirror", "parent": 1005, "size": 21}, {"id": 1006, "name": "chestofdrawers_n", "parent": 1005, "size": 144}, {"id": 1007, "name": "armoire", "parent": 1005, "size": 93}, {"id": 1008, "name": "dresser", "parent": 1005, "size": 206}, {"id": 1009, "name": "nightstand", "parent": 1005, "size": 53}, {"id": 1010, "name": "endtable", "parent": 1005, "size": 91}, {"id": 1011, "name": "cabinet", "parent": 1005, "size": 154}, {"id": 1012, "name": "bag", "parent": 1}, {"id": 1013, "name": "backpack", "parent": 1013, "size": 5}, {"id": 1014, "name": "purse", "parent": 1013, "size": 17}, {"id": 1015, "name": "bag_n", "parent": 1013, "size": 11}, {"id": 1016, "name": "cabinet", "parent": 1}, {"id": 1017, "name": "sideboard", "parent": 1017, "size": 65}, {"id": 1018, "name": "cabinet_n", "parent": 1017, "size": 154}, {"id": 1019, "name": "curiocabinet", "parent": 1017, "size": 10}, {"id": 1020, "name": "filecabinet", "parent": 1017, "size": 19}, {"id": 1021, "name": "coin", "parent": 1}, {"id": 1022, "name": "coin_n", "parent": 1022, "size": 6}, {"id": 1023, "name": "pencil", "parent": 1}, {"id": 1024, "name": "pencil_n", "parent": 1024, "size": 86}, {"id": 1025, "name": "battery", "parent": 1}, {"id": 1026, "name": "battery_n", "parent": 1026, "size": 20}, {"id": 1027, "name": "aabattery", "parent": 1026, "size": 1}, {"id": 1028, "name": "plant", "parent": 1}, {"id": 1029, "name": "pottedplant", "parent": 1029, "size": 187}, {"id": 1030, "name": "plant_n", "parent": 1029, "size": 60}, {"id": 1031, "name": "chair", "parent": 1}, {"id": 1032, "name": "accentchair", "parent": 1032, "size": 50}, {"id": 1033, "name": "officechair", "parent": 1032, "size": 137}, {"id": 1034, "name": "officesidechair", "parent": 1032, "size": 39}, {"id": 1035, "name": "chair_n", "parent": 1032, "size": 307}, {"id": 1036, "name": "sidechair", "parent": 1032, "size": 77}, {"id": 1037, "name": "recliner", "parent": 1032, "size": 30}, {"id": 1038, "name": "chairwithottoman", "parent": 1032, "size": 9}, {"id": 1039, "name": "couch", "parent": 1032, "size": 381}, {"id": 1040, "name": "chaise", "parent": 1032, "size": 39}, {"id": 1041, "name": "beanbag", "parent": 1032, "size": 9}, {"id": 1042, "name": "kneelingchair", "parent": 1032, "size": 1}, {"id": 1043, "name": "candle", "parent": 1}, {"id": 1044, "name": "candle_n", "parent": 1044, "size": 54}, {"id": 1045, "name": "knife", "parent": 1}, {"id": 1046, "name": "knife_n", "parent": 1046, "size": 32}, {"id": 1047, "name": "vase", "parent": 1}, {"id": 1048, "name": "vase_n", "parent": 1048, "size": 168}, {"id": 1049, "name": "lamp", "parent": 1}, {"id": 1050, "name": "ceilinglamp", "parent": 1050, "size": 85}, {"id": 1051, "name": "desklamp", "parent": 1050, "size": 105}, {"id": 1052, "name": "lamp_n", "parent": 1050, "size": 35}, {"id": 1053, "name": "tablelamp", "parent": 1050, "size": 141}, {"id": 1054, "name": "lamppost", "parent": 1050, "size": 24}, {"id": 1055, "name": "floorlamp", "parent": 1050, "size": 201}, {"id": 1056, "name": "walllamp", "parent": 1050, "size": 78}, {"id": 1057, "name": "stapler", "parent": 1}, {"id": 1058, "name": "stapler_n", "parent": 1058, "size": 38}, {"id": 1059, "name": "mediastorage", "parent": 1}, {"id": 1060, "name": "tvstand", "parent": 1060, "size": 29}, {"id": 1061, "name": "wallunit", "parent": 1060, "size": 46}, {"id": 1062, "name": "mediachest", "parent": 1060, "size": 1}, {"id": 1063, "name": "tv", "parent": 1060, "size": 205}, {"id": 1064, "name": "fooditem", "parent": 1}, {"id": 1065, "name": "fooditem_n", "parent": 1065, "size": 86}, {"id": 1066, "name": "cerealbox", "parent": 1065, "size": 25}, {"id": 1067, "name": "foodplate", "parent": 1065, "size": 15}, {"id": 1068, "name": "banana", "parent": 1065, "size": 10}, {"id": 1069, "name": "sandwich", "parent": 1065, "size": 9}, {"id": 1070, "name": "donut", "parent": 1065, "size": 13}, {"id": 1071, "name": "carrot", "parent": 1065, "size": 4}, {"id": 1072, "name": "cookie", "parent": 1065, "size": 6}, {"id": 1073, "name": "apple", "parent": 1065, "size": 5}, {"id": 1074, "name": "cake", "parent": 1065, "size": 10}, {"id": 1075, "name": "pizza", "parent": 1065, "size": 10}, {"id": 1076, "name": "donutbox", "parent": 1065, "size": 8}, {"id": 1077, "name": "fruit", "parent": 1065, "size": 5}, {"id": 1078, "name": "chocolate", "parent": 1065, "size": 1}, {"id": 1079, "name": "bowl", "parent": 1065, "size": 35}, {"id": 1080, "name": "breadslice", "parent": 1065, "size": 4}, {"id": 1081, "name": "fries", "parent": 1065, "size": 1}, {"id": 1082, "name": "milkcarton", "parent": 1065, "size": 2}, {"id": 1083, "name": "plate", "parent": 1065, "size": 9}, {"id": 1084, "name": "egg", "parent": 1065, "size": 2}, {"id": 1085, "name": "cupcake", "parent": 1065, "size": 1}, {"id": 1086, "name": "drinkingutensil", "parent": 1}, {"id": 1087, "name": "mug", "parent": 1087, "size": 51}, {"id": 1088, "name": "cup", "parent": 1087, "size": 41}, {"id": 1089, "name": "teacup", "parent": 1087, "size": 9}, {"id": 1090, "name": "wineglass", "parent": 1087, "size": 10}, {"id": 1091, "name": "drinkingutensil_n", "parent": 1087, "size": 15}, {"id": 1092, "name": "jug", "parent": 1087, "size": 1}, {"id": 1093, "name": "gun", "parent": 1}, {"id": 1094, "name": "gun_n", "parent": 1094, "size": 54}, {"id": 1095, "name": "personstanding", "parent": 1}, {"id": 1096, "name": "personstanding_n", "parent": 1096, "size": 42}, {"id": 1097, "name": "fan", "parent": 1}, {"id": 1098, "name": "fan_n", "parent": 1098, "size": 26}, {"id": 1099, "name": "ceilingfan", "parent": 1098, "size": 3}, {"id": 1100, "name": "mediaplayer", "parent": 1}, {"id": 1101, "name": "mediaplayer_n", "parent": 1101, "size": 61}, {"id": 1102, "name": "toyfigure", "parent": 1}, {"id": 1103, "name": "toyfigure_n", "parent": 1103, "size": 93}, {"id": 1104, "name": "trashbin", "parent": 1}, {"id": 1105, "name": "trashbin_n", "parent": 1105, "size": 117}, {"id": 1106, "name": "counter", "parent": 1}, {"id": 1107, "name": "counter_n", "parent": 1107, "size": 8}, {"id": 1108, "name": "oven", "parent": 1107, "size": 36}, {"id": 1109, "name": "bed", "parent": 1}, {"id": 1110, "name": "singlebed", "parent": 1110, "size": 30}, {"id": 1111, "name": "queenbed", "parent": 1110, "size": 94}, {"id": 1112, "name": "kingbed", "parent": 1110, "size": 14}, {"id": 1113, "name": "doublebed", "parent": 1110, "size": 20}, {"id": 1114, "name": "queenbedwithnightstand", "parent": 1110, "size": 5}, {"id": 1115, "name": "roundbed", "parent": 1110, "size": 2}, {"id": 1116, "name": "bed_n", "parent": 1110, "size": 7}, {"id": 1117, "name": "loftbed", "parent": 1110, "size": 26}, {"id": 1118, "name": "canopybed", "parent": 1110, "size": 6}, {"id": 1119, "name": "posterbed", "parent": 1110, "size": 13}, {"id": 1120, "name": "childbed", "parent": 1110, "size": 4}, {"id": 1121, "name": "crib", "parent": 1110, "size": 8}, {"id": 1122, "name": "cradle", "parent": 1110, "size": 10}, {"id": 1123, "name": "rubikscube", "parent": 1}, {"id": 1124, "name": "rubikscube_n", "parent": 1124, "size": 11}, {"id": 1125, "name": "shirt", "parent": 1}, {"id": 1126, "name": "shirt_n", "parent": 1126, "size": 14}, {"id": 1127, "name": "printer", "parent": 1}, {"id": 1128, "name": "printer_n", "parent": 1128, "size": 43}, {"id": 1129, "name": "oven", "parent": 1}, {"id": 1130, "name": "oven_n", "parent": 1130, "size": 36}, {"id": 1131, "name": "faucet", "parent": 1}, {"id": 1132, "name": "faucet_n", "parent": 1132, "size": 21}, {"id": 1133, "name": "showerhead", "parent": 1132, "size": 3}, {"id": 1134, "name": "computer", "parent": 1}, {"id": 1135, "name": "desktop", "parent": 1135, "size": 65}, {"id": 1136, "name": "laptop", "parent": 1135, "size": 122}, {"id": 1137, "name": "computer_n", "parent": 1135, "size": 9}, {"id": 1138, "name": "bookcase", "parent": 1}, {"id": 1139, "name": "3shelves", "parent": 1139, "size": 13}, {"id": 1140, "name": "5shelves", "parent": 1139, "size": 12}, {"id": 1141, "name": "4shelves", "parent": 1139, "size": 19}, {"id": 1142, "name": "2shelves", "parent": 1139, "size": 9}, {"id": 1143, "name": "1shelves", "parent": 1139, "size": 8}, {"id": 1144, "name": "6shelves", "parent": 1139, "size": 17}, {"id": 1145, "name": "bookcase_n", "parent": 1139, "size": 21}, {"id": 1146, "name": "7shelves", "parent": 1139, "size": 6}, {"id": 1147, "name": "rack", "parent": 1139, "size": 36}, {"id": 1148, "name": "monitor", "parent": 1}, {"id": 1149, "name": "monitor_n", "parent": 1149, "size": 124}, {"id": 1150, "name": "clock", "parent": 1}, {"id": 1151, "name": "clock_n", "parent": 1151, "size": 91}, {"id": 1152, "name": "ottoman", "parent": 1}, {"id": 1153, "name": "ottoman_n", "parent": 1153, "size": 6}, {"id": 1154, "name": "speaker", "parent": 1}, {"id": 1155, "name": "speaker_n", "parent": 1155, "size": 69}, {"id": 1156, "name": "animal", "parent": 1}, {"id": 1157, "name": "bear", "parent": 1157, "size": 17}, {"id": 1158, "name": "horse", "parent": 1157, "size": 18}, {"id": 1159, "name": "fish", "parent": 1157, "size": 13}, {"id": 1160, "name": "bird", "parent": 1157, "size": 9}, {"id": 1161, "name": "elephant", "parent": 1157, "size": 2}, {"id": 1162, "name": "cow", "parent": 1157, "size": 3}, {"id": 1163, "name": "cat", "parent": 1157, "size": 3}, {"id": 1164, "name": "dog", "parent": 1157, "size": 12}, {"id": 1165, "name": "toyfigure", "parent": 1157, "size": 93}, {"id": 1166, "name": "sheep", "parent": 1157, "size": 1}, {"id": 1167, "name": "butterfly", "parent": 1157, "size": 2}, {"id": 1168, "name": "shampoo", "parent": 1}, {"id": 1169, "name": "shampoo_n", "parent": 1169, "size": 4}, {"id": 1170, "name": "shoes", "parent": 1}, {"id": 1171, "name": "shoes_n", "parent": 1171, "size": 28}, {"id": 1172, "name": "bathtub", "parent": 1}, {"id": 1173, "name": "bathtub_n", "parent": 1173, "size": 22}, {"id": 1174, "name": "wallart", "parent": 1}, {"id": 1175, "name": "picture", "parent": 1175, "size": 39}, {"id": 1176, "name": "wallart_n", "parent": 1175, "size": 21}, {"id": 1177, "name": "painting", "parent": 1175, "size": 13}, {"id": 1178, "name": "pictureframe", "parent": 1175, "size": 26}, {"id": 1179, "name": "poster", "parent": 1175, "size": 6}, {"id": 1180, "name": "desk", "parent": 1}, {"id": 1181, "name": "desk_n", "parent": 1181, "size": 191}, {"id": 1182, "name": "ldesk", "parent": 1181, "size": 7}, {"id": 1183, "name": "draftingtable", "parent": 1181, "size": 2}, {"id": 1184, "name": "rack", "parent": 1}, {"id": 1185, "name": "1shelves", "parent": 1185, "size": 8}, {"id": 1186, "name": "4shelves", "parent": 1185, "size": 19}, {"id": 1187, "name": "winerack", "parent": 1185, "size": 11}, {"id": 1188, "name": "coatrack", "parent": 1185, "size": 18}, {"id": 1189, "name": "rack_n", "parent": 1185, "size": 36}, {"id": 1190, "name": "2shelves", "parent": 1185, "size": 9}, {"id": 1191, "name": "potrack", "parent": 1185, "size": 1}, {"id": 1192, "name": "3shelves", "parent": 1185, "size": 13}, {"id": 1193, "name": "videogamecontroller", "parent": 1}, {"id": 1194, "name": "nintendods", "parent": 1194, "size": 15}, {"id": 1195, "name": "videogamecontroller_n", "parent": 1194, "size": 15}, {"id": 1196, "name": "psp", "parent": 1194, "size": 7}, {"id": 1197, "name": "bottle", "parent": 1}, {"id": 1198, "name": "beerbottle", "parent": 1198, "size": 13}, {"id": 1199, "name": "winebottle", "parent": 1198, "size": 25}, {"id": 1200, "name": "bottle_n", "parent": 1198, "size": 49}, {"id": 1201, "name": "drinkbottle", "parent": 1198, "size": 10}, {"id": 1202, "name": "sodacan", "parent": 1}, {"id": 1203, "name": "sodacan_n", "parent": 1203, "size": 44}, {"id": 1204, "name": "disccase", "parent": 1}, {"id": 1205, "name": "disccase_n", "parent": 1205, "size": 9}, {"id": 1206, "name": "ship", "parent": 1}, {"id": 1207, "name": "ship_n", "parent": 1207, "size": 19}, {"id": 1208, "name": "pillbottle", "parent": 1}, {"id": 1209, "name": "pillbottle_n", "parent": 1209, "size": 18}, {"id": 1210, "name": "copier", "parent": 1}, {"id": 1211, "name": "copier_n", "parent": 1211, "size": 8}, {"id": 1212, "name": "refrigerator", "parent": 1}, {"id": 1213, "name": "refrigerator_n", "parent": 1213, "size": 68}, {"id": 1214, "name": "bench", "parent": 1}, {"id": 1215, "name": "bench_n", "parent": 1215, "size": 91}, {"id": 1216, "name": "camera", "parent": 1}, {"id": 1217, "name": "camera_n", "parent": 1217, "size": 69}, {"id": 1218, "name": "dslrcamera", "parent": 1217, "size": 2}, {"id": 1219, "name": "webcam", "parent": 1217, "size": 5}, {"id": 1220, "name": "book", "parent": 1}, {"id": 1221, "name": "book_n", "parent": 1221, "size": 72}, {"id": 1222, "name": "videogameconsole", "parent": 1}, {"id": 1223, "name": "ps3", "parent": 1223, "size": 12}, {"id": 1224, "name": "wii", "parent": 1223, "size": 12}, {"id": 1225, "name": "ps2", "parent": 1223, "size": 7}, {"id": 1226, "name": "videogameconsole_n", "parent": 1223, "size": 27}, {"id": 1227, "name": "gamecube", "parent": 1223, "size": 7}, {"id": 1228, "name": "ps", "parent": 1223, "size": 2}, {"id": 1229, "name": "xbox360", "parent": 1223, "size": 2}, {"id": 1230, "name": "xbox", "parent": 1223, "size": 6}, {"id": 1231, "name": "usbstick", "parent": 1}, {"id": 1232, "name": "usbstick_n", "parent": 1232, "size": 40}, {"id": 1233, "name": "eraser", "parent": 1}, {"id": 1234, "name": "eraser_n", "parent": 1234, "size": 14}, {"id": 1235, "name": "phone", "parent": 1}, {"id": 1236, "name": "cellphone", "parent": 1236, "size": 122}, {"id": 1237, "name": "telephone", "parent": 1236, "size": 39}, {"id": 1238, "name": "ipod", "parent": 1236, "size": 50}, {"id": 1239, "name": "teapot", "parent": 1}, {"id": 1240, "name": "teapot_n", "parent": 1240, "size": 9}, {"id": 1241, "name": "pen", "parent": 1}, {"id": 1242, "name": "pen_n", "parent": 1242, "size": 32}, {"id": 1243, "name": "microwave", "parent": 1}, {"id": 1244, "name": "microwave_n", "parent": 1244, "size": 24}, {"id": 1245, "name": "piano", "parent": 1}, {"id": 1246, "name": "piano_n", "parent": 1246, "size": 56}, {"id": 1247, "name": "paperbox", "parent": 1}, {"id": 1248, "name": "paperbox_n", "parent": 1248, "size": 32}, {"id": 1249, "name": "sword", "parent": 1}, {"id": 1250, "name": "sword_n", "parent": 1250, "size": 39}, {"id": 1251, "name": "computermouse", "parent": 1}, {"id": 1252, "name": "computermouse_n", "parent": 1252, "size": 23}, {"id": 1253, "name": "stool", "parent": 1}, {"id": 1254, "name": "barstool", "parent": 1254, "size": 66}, {"id": 1255, "name": "stool_n", "parent": 1254, "size": 28}, {"id": 1256, "name": "lightswitch", "parent": 1}, {"id": 1257, "name": "lightswitch_n", "parent": 1257, "size": 28}, {"id": 1258, "name": "cabling", "parent": 1}, {"id": 1259, "name": "cabling_n", "parent": 1259, "size": 1}, {"id": 1260, "name": "ipod", "parent": 1259, "size": 50}, {"id": 1261, "name": "bowl", "parent": 1}, {"id": 1262, "name": "bowl_n", "parent": 1262, "size": 35}, {"id": 1263, "name": "fooditem", "parent": 1262, "size": 86}, {"id": 1264, "name": "fruitbowl", "parent": 1262, "size": 7}, {"id": 1265, "name": "car", "parent": 1}, {"id": 1266, "name": "car_n", "parent": 1266, "size": 18}, {"id": 1267, "name": "toyfigure", "parent": 1266, "size": 93}, {"id": 1268, "name": "guitar", "parent": 1}, {"id": 1269, "name": "guitar_n", "parent": 1269, "size": 66}, {"id": 1270, "name": "gametable", "parent": 1}, {"id": 1271, "name": "gametable_n", "parent": 1271, "size": 25}, {"id": 1272, "name": "mattress", "parent": 1}, {"id": 1273, "name": "mattress_n", "parent": 1273, "size": 18}, {"id": 1274, "name": "toilet", "parent": 1}, {"id": 1275, "name": "toilet_n", "parent": 1275, "size": 52}, {"id": 1276, "name": "fireplace", "parent": 1}, {"id": 1277, "name": "fireplace_n", "parent": 1277, "size": 38}, {"id": 1278, "name": "ladder", "parent": 1}, {"id": 1279, "name": "ladder_n", "parent": 1279, "size": 4}, {"id": 1280, "name": "suitcase", "parent": 1}, {"id": 1281, "name": "suitcase_n", "parent": 1281, "size": 16}, {"id": 1282, "name": "pianokeyboard", "parent": 1}, {"id": 1283, "name": "pianokeyboard_n", "parent": 1283, "size": 28}, {"id": 1284, "name": "books", "parent": 1}, {"id": 1285, "name": "books_n", "parent": 1285, "size": 25}, {"id": 1286, "name": "airplane", "parent": 1}, {"id": 1287, "name": "airplane_n", "parent": 1287, "size": 34}, {"id": 1288, "name": "toyfigure", "parent": 1287, "size": 93}, {"id": 1289, "name": "washer", "parent": 1}, {"id": 1290, "name": "washer_n", "parent": 1290, "size": 13}, {"id": 1291, "name": "bucket", "parent": 1}, {"id": 1292, "name": "bucket_n", "parent": 1292, "size": 18}, {"id": 1293, "name": "powerstrip", "parent": 1}, {"id": 1294, "name": "powerstrip_n", "parent": 1294, "size": 6}, {"id": 1295, "name": "glasses", "parent": 1}, {"id": 1296, "name": "glasses_n", "parent": 1296, "size": 4}, {"id": 1297, "name": "basket", "parent": 1}, {"id": 1298, "name": "basket_n", "parent": 1298, "size": 23}, {"id": 1299, "name": "curtain", "parent": 1}, {"id": 1300, "name": "curtain_n", "parent": 1300, "size": 36}, {"id": 1301, "name": "pillow", "parent": 1}, {"id": 1302, "name": "pillow_n", "parent": 1302, "size": 25}, {"id": 1303, "name": "hammer", "parent": 1}, {"id": 1304, "name": "hammer_n", "parent": 1304, "size": 27}, {"id": 1305, "name": "easel", "parent": 1}, {"id": 1306, "name": "easel_n", "parent": 1306, "size": 12}, {"id": 1307, "name": "booth", "parent": 1}, {"id": 1308, "name": "booth_n", "parent": 1308, "size": 12}, {"id": 1309, "name": "vanity", "parent": 1}, {"id": 1310, "name": "vanity_n", "parent": 1310, "size": 4}, {"id": 1311, "name": "helicopter", "parent": 1}, {"id": 1312, "name": "helicopter_n", "parent": 1312, "size": 23}, {"id": 1313, "name": "pedestal", "parent": 1}, {"id": 1314, "name": "pedestal_n", "parent": 1314, "size": 4}, {"id": 1315, "name": "filecabinet", "parent": 1}, {"id": 1316, "name": "filecabinet_n", "parent": 1316, "size": 19}, {"id": 1317, "name": "headphones", "parent": 1}, {"id": 1318, "name": "headphones_n", "parent": 1318, "size": 25}, {"id": 1319, "name": "ipod", "parent": 1318, "size": 50}, {"id": 1320, "name": "board", "parent": 1}, {"id": 1321, "name": "board_n", "parent": 1321, "size": 5}, {"id": 1322, "name": "ring", "parent": 1}, {"id": 1323, "name": "ring_n", "parent": 1323, "size": 12}, {"id": 1324, "name": "notepad", "parent": 1}, {"id": 1325, "name": "notepad_n", "parent": 1325, "size": 6}, {"id": 1326, "name": "mirror", "parent": 1}, {"id": 1327, "name": "mirror_n", "parent": 1327, "size": 26}, {"id": 1328, "name": "calculator", "parent": 1}, {"id": 1329, "name": "calculator_n", "parent": 1329, "size": 27}, {"id": 1330, "name": "keyboard", "parent": 1}, {"id": 1331, "name": "keyboard_n", "parent": 1331, "size": 20}, {"id": 1332, "name": "sink", "parent": 1}, {"id": 1333, "name": "sink_n", "parent": 1333, "size": 39}, {"id": 1334, "name": "ball", "parent": 1}, {"id": 1335, "name": "ball_n", "parent": 1335, "size": 24}, {"id": 1336, "name": "fork", "parent": 1}, {"id": 1337, "name": "fork_n", "parent": 1337, "size": 11}, {"id": 1338, "name": "watch", "parent": 1}, {"id": 1339, "name": "watch_n", "parent": 1339, "size": 6}, {"id": 1340, "name": "pictureframe", "parent": 1}, {"id": 1341, "name": "pictureframe_n", "parent": 1341, "size": 26}, {"id": 1342, "name": "coaster", "parent": 1}, {"id": 1343, "name": "coaster_n", "parent": 1343, "size": 2}, {"id": 1344, "name": "toiletpaper", "parent": 1}, {"id": 1345, "name": "toiletpaper_n", "parent": 1345, "size": 30}, {"id": 1346, "name": "door", "parent": 1}, {"id": 1347, "name": "door_n", "parent": 1347, "size": 2}, {"id": 1348, "name": "motorcycle", "parent": 1}, {"id": 1349, "name": "motorcycle_n", "parent": 1349, "size": 10}, {"id": 1350, "name": "hanger", "parent": 1}, {"id": 1351, "name": "hanger_n", "parent": 1351, "size": 7}, {"id": 1352, "name": "cage", "parent": 1}, {"id": 1353, "name": "cage_n", "parent": 1353, "size": 11}, {"id": 1354, "name": "credenza", "parent": 1}, {"id": 1355, "name": "credenza_n", "parent": 1355, "size": 14}, {"id": 1356, "name": "soapbar", "parent": 1}, {"id": 1357, "name": "soapbar_n", "parent": 1357, "size": 5}, {"id": 1358, "name": "truck", "parent": 1}, {"id": 1359, "name": "truck_n", "parent": 1359, "size": 20}, {"id": 1360, "name": "window", "parent": 1}, {"id": 1361, "name": "window_n", "parent": 1361, "size": 10}, {"id": 1362, "name": "hat", "parent": 1}, {"id": 1363, "name": "hat_n", "parent": 1363, "size": 7}, {"id": 1364, "name": "powersocket", "parent": 1}, {"id": 1365, "name": "powersocket_n", "parent": 1365, "size": 8}, {"id": 1366, "name": "pan", "parent": 1}, {"id": 1367, "name": "pan_n", "parent": 1367, "size": 19}, {"id": 1368, "name": "decorativeaccessory", "parent": 1}, {"id": 1369, "name": "decorativeaccessory_n", "parent": 1369, "size": 4}, {"id": 1370, "name": "phonebooth", "parent": 1}, {"id": 1371, "name": "phonebooth_n", "parent": 1371, "size": 5}, {"id": 1372, "name": "umbrella", "parent": 1}, {"id": 1373, "name": "umbrella_n", "parent": 1373, "size": 18}, {"id": 1374, "name": "bicycle", "parent": 1}, {"id": 1375, "name": "bicycle_n", "parent": 1375, "size": 6}, {"id": 1376, "name": "headboard", "parent": 1}, {"id": 1377, "name": "headboard_n", "parent": 1377, "size": 8}, {"id": 1378, "name": "radio", "parent": 1}, {"id": 1379, "name": "radio_n", "parent": 1379, "size": 12}, {"id": 1380, "name": "tableclock", "parent": 1379, "size": 1}, {"id": 1381, "name": "showerhead", "parent": 1}, {"id": 1382, "name": "faucet", "parent": 1382, "size": 21}, {"id": 1383, "name": "closet", "parent": 1}, {"id": 1384, "name": "wardrobe", "parent": 1384, "size": 4}, {"id": 1385, "name": "armoire", "parent": 1384, "size": 93}, {"id": 1386, "name": "violin", "parent": 1}, {"id": 1387, "name": "violin_n", "parent": 1387, "size": 9}, {"id": 1388, "name": "tissuebox", "parent": 1}, {"id": 1389, "name": "tissuebox_n", "parent": 1389, "size": 24}, {"id": 1390, "name": "plate", "parent": 1}, {"id": 1391, "name": "plate_n", "parent": 1391, "size": 9}, {"id": 1392, "name": "tank", "parent": 1}, {"id": 1393, "name": "tank_n", "parent": 1393, "size": 14}, {"id": 1394, "name": "toyfigure", "parent": 1393, "size": 93}, {"id": 1395, "name": "controller", "parent": 1}, {"id": 1396, "name": "controller_n", "parent": 1396, "size": 2}, {"id": 1397, "name": "harp", "parent": 1}, {"id": 1398, "name": "harp_n", "parent": 1398, "size": 1}, {"id": 1399, "name": "cap", "parent": 1}, {"id": 1400, "name": "cap_n", "parent": 1400, "size": 16}, {"id": 1401, "name": "kettle", "parent": 1}, {"id": 1402, "name": "kettle_n", "parent": 1402, "size": 1}, {"id": 1403, "name": "spoon", "parent": 1}, {"id": 1404, "name": "spoon_n", "parent": 1404, "size": 11}, {"id": 1405, "name": "scissors", "parent": 1}, {"id": 1406, "name": "scissors_n", "parent": 1406, "size": 6}, {"id": 1407, "name": "oventop", "parent": 1}, {"id": 1408, "name": "oventop_n", "parent": 1408, "size": 4}, {"id": 1409, "name": "mediadiscs", "parent": 1}, {"id": 1410, "name": "mediadiscs_n", "parent": 1410, "size": 3}, {"id": 1411, "name": "screwdriver", "parent": 1}, {"id": 1412, "name": "screwdriver_n", "parent": 1412, "size": 1}, {"id": 1413, "name": "rug", "parent": 1}, {"id": 1414, "name": "rug_n", "parent": 1414, "size": 2}, {"id": 1415, "name": "bus", "parent": 1}, {"id": 1416, "name": "bus_n", "parent": 1416, "size": 3}, {"id": 1417, "name": "shower", "parent": 1}, {"id": 1418, "name": "shower_n", "parent": 1418, "size": 7}, {"id": 1419, "name": "marker", "parent": 1}, {"id": 1420, "name": "marker_n", "parent": 1420, "size": 2}, {"id": 1421, "name": "guitarstand", "parent": 1}, {"id": 1422, "name": "guitarstand_n", "parent": 1422, "size": 4}, {"id": 1423, "name": "paperclip", "parent": 1}, {"id": 1424, "name": "paperclip_n", "parent": 1424, "size": 8}, {"id": 1425, "name": "statue", "parent": 1}, {"id": 1426, "name": "statue_n", "parent": 1426, "size": 12}, {"id": 1427, "name": "wallet", "parent": 1}, {"id": 1428, "name": "wallet_n", "parent": 1428, "size": 1}, {"id": 1429, "name": "canopener", "parent": 1}, {"id": 1430, "name": "canopener_n", "parent": 1430, "size": 2}, {"id": 1431, "name": "canister", "parent": 1}, {"id": 1432, "name": "canister_n", "parent": 1432, "size": 2}, {"id": 1433, "name": "cassette", "parent": 1}, {"id": 1434, "name": "cassette_n", "parent": 1434, "size": 3}, {"id": 1435, "name": "blind", "parent": 1}, {"id": 1436, "name": "blind_n", "parent": 1436, "size": 2}, {"id": 1437, "name": "tabledesklamp", "parent": 1}, {"id": 1438, "name": "tablelamp", "parent": 1438, "size": 141}, {"id": 1439, "name": "desklamp", "parent": 1438, "size": 105}, {"id": 1440, "name": "thermostat", "parent": 1}, {"id": 1441, "name": "thermostat_n", "parent": 1441, "size": 3}, {"id": 1442, "name": "magnet", "parent": 1}, {"id": 1443, "name": "magnet_n", "parent": 1443, "size": 8}, {"id": 1444, "name": "plotter", "parent": 1}, {"id": 1445, "name": "plotter_n", "parent": 1445, "size": 1}, {"id": 1446, "name": "lectern", "parent": 1}, {"id": 1447, "name": "lectern_n", "parent": 1447, "size": 1}, {"id": 1448, "name": "bidet", "parent": 1}, {"id": 1449, "name": "bidet_n", "parent": 1449, "size": 1}]